{"nodes":[{"label":"WAB","x":-136.05616760253906,"y":-251.2899169921875,"id":"WAB","clusterName":"Ships","attributes":{"Industry":"Ships","Centrality Measures":"","Closeness Centrality":"1.0","Harmonic Closeness Centrality":"1.0","Betweenness Centrality":"0.333","Eigenvector Centrality":"1.0","Other Measures":"","Degree":"4.0","Weighted Degree":"311.0","Eccentricity":"1.0"},"color":"rgb(255,127,83)","size":48.52631759643555},{"label":"GBX","x":-37.65180969238281,"y":282.9748840332031,"id":"GBX","clusterName":"Ships","attributes":{"Industry":"Ships","Centrality Measures":"","Closeness Centrality":"1.0","Harmonic Closeness Centrality":"1.0","Betweenness Centrality":"0.333","Eigenvector Centrality":"1.0","Other Measures":"","Degree":"4.0","Weighted Degree":"421.0","Eccentricity":"1.0"},"color":"rgb(255,127,83)","size":62.42105484008789},{"label":"HII","x":257.7334289550781,"y":123.41555786132812,"id":"HII","clusterName":"Ships","attributes":{"Industry":"Ships","Centrality Measures":"","Closeness Centrality":"0.8","Harmonic Closeness Centrality":"0.875","Betweenness Centrality":"0.0","Eigenvector Centrality":"0.823","Other Measures":"","Degree":"3.0","Weighted Degree":"6.0","Eccentricity":"2.0"},"color":"rgb(255,127,83)","size":10.0},{"label":"RAIL","x":-280.7572937011719,"y":51.65101623535156,"id":"RAIL","clusterName":"Ships","attributes":{"Industry":"Ships","Centrality Measures":"","Closeness Centrality":"1.0","Harmonic Closeness Centrality":"1.0","Betweenness Centrality":"0.333","Eigenvector Centrality":"1.0","Other Measures":"","Degree":"4.0","Weighted Degree":"341.0","Eccentricity":"1.0"},"color":"rgb(255,127,83)","size":52.31578826904297},{"label":"TRN","x":196.73184204101562,"y":-206.7515411376953,"id":"TRN","clusterName":"Ships","attributes":{"Industry":"Ships","Centrality Measures":"","Closeness Centrality":"0.8","Harmonic Closeness Centrality":"0.875","Betweenness Centrality":"0.0","Eigenvector Centrality":"0.823","Other Measures":"","Degree":"3.0","Weighted Degree":"481.0","Eccentricity":"2.0"},"color":"rgb(255,127,83)","size":70.0}],"edges":[{"source":"TRN","target":"GBX","id":"1819130","attributes":{"sourceColor":"rgb(255,127,83)","targetColor":"rgb(255,127,83)"},"color":"rgb(255,127,83)","size":195.0},{"source":"RAIL","target":"GBX","id":"1819132","attributes":{"sourceColor":"rgb(255,127,83)","targetColor":"rgb(255,127,83)"},"color":"rgb(255,127,83)","size":124.0},{"source":"WAB","target":"RAIL","id":"1819138","attributes":{"sourceColor":"rgb(255,127,83)","targetColor":"rgb(255,127,83)"},"color":"rgb(255,127,83)","size":69.0},{"source":"HII","target":"GBX","id":"1819129","attributes":{"sourceColor":"rgb(255,127,83)","targetColor":"rgb(255,127,83)"},"color":"rgb(255,127,83)","size":2.0},{"source":"RAIL","target":"HII","id":"1819134","attributes":{"sourceColor":"rgb(255,127,83)","targetColor":"rgb(255,127,83)"},"color":"rgb(255,127,83)","size":2.0},{"source":"WAB","target":"HII","id":"1819135","attributes":{"sourceColor":"rgb(255,127,83)","targetColor":"rgb(255,127,83)"},"color":"rgb(255,127,83)","size":2.0},{"source":"TRN","target":"RAIL","id":"1819137","attributes":{"sourceColor":"rgb(255,127,83)","targetColor":"rgb(255,127,83)"},"color":"rgb(255,127,83)","size":146.0},{"source":"WAB","target":"TRN","id":"1819142","attributes":{"sourceColor":"rgb(255,127,83)","targetColor":"rgb(255,127,83)"},"color":"rgb(255,127,83)","size":140.0},{"source":"WAB","target":"GBX","id":"1819131","attributes":{"sourceColor":"rgb(255,127,83)","targetColor":"rgb(255,127,83)"},"color":"rgb(255,127,83)","size":100.0}]}