{"nodes":[{"label":"PCAR","x":-471.41143798828125,"y":-188.61911010742188,"id":"PCAR","clusterName":"Autos","attributes":{"Industry":"Autos","Centrality Measures":"","Closeness Centrality":"0.672","Harmonic Closeness Centrality":"0.756","Betweenness Centrality":"11.655","Eigenvector Centrality":"0.659","Other Measures":"","Degree":"21.0","Weighted Degree":"587.0","Eccentricity":"2.0"},"color":"rgb(255,131,255)","size":10.906400680541992},{"label":"SORL","x":254.2355499267578,"y":-457.34954833984375,"id":"SORL","clusterName":"Autos","attributes":{"Industry":"Autos","Centrality Measures":"","Closeness Centrality":"0.621","Harmonic Closeness Centrality":"0.695","Betweenness Centrality":"7.164","Eigenvector Centrality":"0.514","Other Measures":"","Degree":"16.0","Weighted Degree":"373.0","Eccentricity":"2.0"},"color":"rgb(255,131,255)","size":10.575958251953125},{"label":"SPAR","x":480.0926818847656,"y":-100.12421417236328,"id":"SPAR","clusterName":"Autos","attributes":{"Industry":"Autos","Centrality Measures":"","Closeness Centrality":"0.661","Harmonic Closeness Centrality":"0.752","Betweenness Centrality":"23.578","Eigenvector Centrality":"0.581","Other Measures":"","Degree":"21.0","Weighted Degree":"646.0","Eccentricity":"3.0"},"color":"rgb(255,131,255)","size":10.997503280639648},{"label":"TEN","x":273.0199279785156,"y":-34.597190856933594,"id":"TEN","clusterName":"Autos","attributes":{"Industry":"Autos","Centrality Measures":"","Closeness Centrality":"0.707","Harmonic Closeness Centrality":"0.793","Betweenness Centrality":"8.987","Eigenvector Centrality":"0.809","Other Measures":"","Degree":"24.0","Weighted Degree":"1460.0","Eccentricity":"2.0"},"color":"rgb(255,131,255)","size":12.254420280456543},{"label":"WNC","x":431.5834045410156,"y":-297.4286193847656,"id":"WNC","clusterName":"Autos","attributes":{"Industry":"Autos","Centrality Measures":"","Closeness Centrality":"0.651","Harmonic Closeness Centrality":"0.732","Betweenness Centrality":"8.323","Eigenvector Centrality":"0.625","Other Measures":"","Degree":"19.0","Weighted Degree":"349.0","Eccentricity":"2.0"},"color":"rgb(255,131,255)","size":10.538899421691895},{"label":"BWA","x":44.82724380493164,"y":-153.89453125,"id":"BWA","clusterName":"Autos","attributes":{"Industry":"Autos","Centrality Measures":"","Closeness Centrality":"0.774","Harmonic Closeness Centrality":"0.854","Betweenness Centrality":"20.836","Eigenvector Centrality":"0.923","Other Measures":"","Degree":"29.0","Weighted Degree":"1644.0","Eccentricity":"2.0"},"color":"rgb(255,131,255)","size":12.538538932800293},{"label":"REVG","x":592.7913818359375,"y":368.12762451171875,"id":"REVG","clusterName":"Autos","attributes":{"Industry":"Autos","Centrality Measures":"","Closeness Centrality":"0.569","Harmonic Closeness Centrality":"0.63","Betweenness Centrality":"0.978","Eigenvector Centrality":"0.373","Other Measures":"","Degree":"11.0","Weighted Degree":"235.0","Eccentricity":"3.0"},"color":"rgb(255,131,255)","size":10.362869262695312},{"label":"BGG","x":488.3202209472656,"y":-504.1162414550781,"id":"BGG","clusterName":"Autos","attributes":{"Industry":"Autos","Centrality Measures":"","Closeness Centrality":"0.554","Harmonic Closeness Centrality":"0.606","Betweenness Centrality":"1.305","Eigenvector Centrality":"0.309","Other Measures":"","Degree":"9.0","Weighted Degree":"185.0","Eccentricity":"3.0"},"color":"rgb(255,131,255)","size":10.285662651062012},{"label":"CVGI","x":62.94883346557617,"y":-642.7083129882812,"id":"CVGI","clusterName":"Autos","attributes":{"Industry":"Autos","Centrality Measures":"","Closeness Centrality":"0.547","Harmonic Closeness Centrality":"0.593","Betweenness Centrality":"2.007","Eigenvector Centrality":"0.24","Other Measures":"","Degree":"8.0","Weighted Degree":"317.0","Eccentricity":"3.0"},"color":"rgb(255,131,255)","size":10.489486694335938},{"label":"LEA","x":-90.27191162109375,"y":218.42808532714844,"id":"LEA","clusterName":"Autos","attributes":{"Industry":"Autos","Centrality Measures":"","Closeness Centrality":"0.804","Harmonic Closeness Centrality":"0.878","Betweenness Centrality":"35.991","Eigenvector Centrality":"0.951","Other Measures":"","Degree":"31.0","Weighted Degree":"1644.0","Eccentricity":"2.0"},"color":"rgb(255,131,255)","size":12.538538932800293},{"label":"ALV","x":284.0831298828125,"y":177.9207763671875,"id":"ALV","clusterName":"Autos","attributes":{"Industry":"Autos","Centrality Measures":"","Closeness Centrality":"0.719","Harmonic Closeness Centrality":"0.805","Betweenness Centrality":"15.646","Eigenvector Centrality":"0.81","Other Measures":"","Degree":"25.0","Weighted Degree":"797.0","Eccentricity":"2.0"},"color":"rgb(255,131,255)","size":11.230666160583496},{"label":"PII","x":227.0068817138672,"y":-232.5181884765625,"id":"PII","clusterName":"Autos","attributes":{"Industry":"Autos","Centrality Measures":"","Closeness Centrality":"0.661","Harmonic Closeness Centrality":"0.744","Betweenness Centrality":"7.61","Eigenvector Centrality":"0.667","Other Measures":"","Degree":"20.0","Weighted Degree":"905.0","Eccentricity":"2.0"},"color":"rgb(255,131,255)","size":11.397431373596191},{"label":"THO","x":119.86504364013672,"y":302.0116882324219,"id":"THO","clusterName":"Autos","attributes":{"Industry":"Autos","Centrality Measures":"","Closeness Centrality":"0.661","Harmonic Closeness Centrality":"0.744","Betweenness Centrality":"12.393","Eigenvector Centrality":"0.615","Other Measures":"","Degree":"20.0","Weighted Degree":"1074.0","Eccentricity":"2.0"},"color":"rgb(255,131,255)","size":11.658388137817383},{"label":"WGO","x":-299.1138916015625,"y":126.26634216308594,"id":"WGO","clusterName":"Autos","attributes":{"Industry":"Autos","Centrality Measures":"","Closeness Centrality":"0.641","Harmonic Closeness Centrality":"0.72","Betweenness Centrality":"4.926","Eigenvector Centrality":"0.619","Other Measures":"","Degree":"18.0","Weighted Degree":"1079.0","Eccentricity":"2.0"},"color":"rgb(255,131,255)","size":11.666109085083008},{"label":"CLC","x":-663.1450805664062,"y":-272.5693054199219,"id":"CLC","clusterName":"Autos","attributes":{"Industry":"Autos","Centrality Measures":"","Closeness Centrality":"0.513","Harmonic Closeness Centrality":"0.549","Betweenness Centrality":"0.862","Eigenvector Centrality":"0.146","Other Measures":"","Degree":"5.0","Weighted Degree":"83.0","Eccentricity":"3.0"},"color":"rgb(255,131,255)","size":10.128162384033203},{"label":"LDL","x":-722.6776123046875,"y":-41.04957580566406,"id":"LDL","clusterName":"Autos","attributes":{"Industry":"Autos","Centrality Measures":"","Closeness Centrality":"0.5","Harmonic Closeness Centrality":"0.541","Betweenness Centrality":"0.593","Eigenvector Centrality":"0.121","Other Measures":"","Degree":"5.0","Weighted Degree":"49.0","Eccentricity":"3.0"},"color":"rgb(255,131,255)","size":10.075661659240723},{"label":"MTOR","x":47.78253936767578,"y":-390.35369873046875,"id":"MTOR","clusterName":"Autos","attributes":{"Industry":"Autos","Centrality Measures":"","Closeness Centrality":"0.788","Harmonic Closeness Centrality":"0.866","Betweenness Centrality":"23.201","Eigenvector Centrality":"0.947","Other Measures":"","Degree":"30.0","Weighted Degree":"773.0","Eccentricity":"2.0"},"color":"rgb(255,131,255)","size":11.193607330322266},{"label":"VC","x":-314.5762023925781,"y":-349.84033203125,"id":"VC","clusterName":"Autos","attributes":{"Industry":"Autos","Centrality Measures":"","Closeness Centrality":"0.745","Harmonic Closeness Centrality":"0.829","Betweenness Centrality":"23.253","Eigenvector Centrality":"0.85","Other Measures":"","Degree":"27.0","Weighted Degree":"695.0","Eccentricity":"2.0"},"color":"rgb(255,131,255)","size":11.073165893554688},{"label":"TEX","x":-343.8255310058594,"y":-569.3240966796875,"id":"TEX","clusterName":"Autos","attributes":{"Industry":"Autos","Centrality Measures":"","Closeness Centrality":"0.651","Harmonic Closeness Centrality":"0.732","Betweenness Centrality":"15.529","Eigenvector Centrality":"0.606","Other Measures":"","Degree":"19.0","Weighted Degree":"311.0","Eccentricity":"2.0"},"color":"rgb(255,131,255)","size":10.480222702026367},{"label":"F","x":-113.30992126464844,"y":-7.306534767150879,"id":"F","clusterName":"Autos","attributes":{"Industry":"Autos","Centrality Measures":"","Closeness Centrality":"0.837","Harmonic Closeness Centrality":"0.902","Betweenness Centrality":"37.695","Eigenvector Centrality":"1.0","Other Measures":"","Degree":"33.0","Weighted Degree":"38793.0","Eccentricity":"2.0"},"color":"rgb(255,131,255)","size":69.90117645263672},{"label":"SRI","x":173.8402862548828,"y":501.04620361328125,"id":"SRI","clusterName":"Autos","attributes":{"Industry":"Autos","Centrality Measures":"","Closeness Centrality":"0.641","Harmonic Closeness Centrality":"0.72","Betweenness Centrality":"4.8","Eigenvector Centrality":"0.609","Other Measures":"","Degree":"18.0","Weighted Degree":"340.0","Eccentricity":"2.0"},"color":"rgb(255,131,255)","size":10.525001525878906},{"label":"HAR","x":691.2655639648438,"y":-69.17736053466797,"id":"HAR","clusterName":"Autos","attributes":{"Industry":"Autos","Centrality Measures":"","Closeness Centrality":"0.577","Harmonic Closeness Centrality":"0.65","Betweenness Centrality":"3.209","Eigenvector Centrality":"0.457","Other Measures":"","Degree":"13.0","Weighted Degree":"286.0","Eccentricity":"3.0"},"color":"rgb(255,131,255)","size":10.441618919372559},{"label":"STRT","x":281.2137451171875,"y":-655.8235473632812,"id":"STRT","clusterName":"Autos","attributes":{"Industry":"Autos","Centrality Measures":"","Closeness Centrality":"0.612","Harmonic Closeness Centrality":"0.691","Betweenness Centrality":"8.655","Eigenvector Centrality":"0.508","Other Measures":"","Degree":"16.0","Weighted Degree":"179.0","Eccentricity":"3.0"},"color":"rgb(255,131,255)","size":10.276397705078125},{"label":"WBC","x":-113.17029571533203,"y":-506.1968688964844,"id":"WBC","clusterName":"Autos","attributes":{"Industry":"Autos","Centrality Measures":"","Closeness Centrality":"0.707","Harmonic Closeness Centrality":"0.793","Betweenness Centrality":"12.723","Eigenvector Centrality":"0.792","Other Measures":"","Degree":"24.0","Weighted Degree":"404.0","Eccentricity":"2.0"},"color":"rgb(255,131,255)","size":10.623826026916504},{"label":"MLR","x":204.17971801757812,"y":698.362548828125,"id":"MLR","clusterName":"Autos","attributes":{"Industry":"Autos","Centrality Measures":"","Closeness Centrality":"0.532","Harmonic Closeness Centrality":"0.593","Betweenness Centrality":"3.078","Eigenvector Centrality":"0.223","Other Measures":"","Degree":"9.0","Weighted Degree":"36.0","Eccentricity":"3.0"},"color":"rgb(255,131,255)","size":10.055588722229004},{"label":"MNTX","x":-581.0158081054688,"y":426.2917785644531,"id":"MNTX","clusterName":"Autos","attributes":{"Industry":"Autos","Centrality Measures":"","Closeness Centrality":"0.547","Harmonic Closeness Centrality":"0.602","Betweenness Centrality":"2.862","Eigenvector Centrality":"0.244","Other Measures":"","Degree":"9.0","Weighted Degree":"57.0","Eccentricity":"3.0"},"color":"rgb(255,131,255)","size":10.088014602661133},{"label":"GM","x":82.76011657714844,"y":75.59559631347656,"id":"GM","clusterName":"Autos","attributes":{"Industry":"Autos","Centrality Measures":"","Closeness Centrality":"0.788","Harmonic Closeness Centrality":"0.866","Betweenness Centrality":"38.782","Eigenvector Centrality":"0.913","Other Measures":"","Degree":"30.0","Weighted Degree":"38857.0","Eccentricity":"2.0"},"color":"rgb(255,131,255)","size":70.0},{"label":"GT","x":-294.4923400878906,"y":-95.03205871582031,"id":"GT","clusterName":"Autos","attributes":{"Industry":"Autos","Centrality Measures":"","Closeness Centrality":"0.672","Harmonic Closeness Centrality":"0.756","Betweenness Centrality":"9.763","Eigenvector Centrality":"0.71","Other Measures":"","Degree":"21.0","Weighted Degree":"1253.0","Eccentricity":"2.0"},"color":"rgb(255,131,255)","size":11.934786796569824},{"label":"SUP","x":411.6692199707031,"y":560.6774291992188,"id":"SUP","clusterName":"Autos","attributes":{"Industry":"Autos","Centrality Measures":"","Closeness Centrality":"0.661","Harmonic Closeness Centrality":"0.744","Betweenness Centrality":"15.917","Eigenvector Centrality":"0.663","Other Measures":"","Degree":"20.0","Weighted Degree":"282.0","Eccentricity":"2.0"},"color":"rgb(255,131,255)","size":10.435442924499512},{"label":"KNDI","x":-518.6798095703125,"y":43.89287567138672,"id":"KNDI","clusterName":"Autos","attributes":{"Industry":"Autos","Centrality Measures":"","Closeness Centrality":"0.621","Harmonic Closeness Centrality":"0.695","Betweenness Centrality":"13.897","Eigenvector Centrality":"0.462","Other Measures":"","Degree":"16.0","Weighted Degree":"380.0","Eccentricity":"2.0"},"color":"rgb(255,131,255)","size":10.586767196655273},{"label":"LCII","x":-211.19415283203125,"y":625.7291870117188,"id":"LCII","clusterName":"Autos","attributes":{"Industry":"Autos","Centrality Measures":"","Closeness Centrality":"0.586","Harmonic Closeness Centrality":"0.654","Betweenness Centrality":"3.34","Eigenvector Centrality":"0.434","Other Measures":"","Degree":"13.0","Weighted Degree":"316.0","Eccentricity":"3.0"},"color":"rgb(255,131,255)","size":10.487942695617676},{"label":"AXL","x":-242.79405212402344,"y":370.98675537109375,"id":"AXL","clusterName":"Autos","attributes":{"Industry":"Autos","Centrality Measures":"","Closeness Centrality":"0.683","Harmonic Closeness Centrality":"0.768","Betweenness Centrality":"8.466","Eigenvector Centrality":"0.746","Other Measures":"","Degree":"22.0","Weighted Degree":"754.0","Eccentricity":"2.0"},"color":"rgb(255,131,255)","size":11.16426944732666},{"label":"CAAS","x":-25.752267837524414,"y":695.8956298828125,"id":"CAAS","clusterName":"Autos","attributes":{"Industry":"Autos","Centrality Measures":"","Closeness Centrality":"0.532","Harmonic Closeness Centrality":"0.577","Betweenness Centrality":"0.314","Eigenvector Centrality":"0.229","Other Measures":"","Degree":"7.0","Weighted Degree":"248.0","Eccentricity":"3.0"},"color":"rgb(255,131,255)","size":10.382942199707031},{"label":"CPS","x":388.8592834472656,"y":362.47088623046875,"id":"CPS","clusterName":"Autos","attributes":{"Industry":"Autos","Centrality Measures":"","Closeness Centrality":"0.621","Harmonic Closeness Centrality":"0.695","Betweenness Centrality":"1.674","Eigenvector Centrality":"0.585","Other Measures":"","Degree":"16.0","Weighted Degree":"331.0","Eccentricity":"2.0"},"color":"rgb(255,131,255)","size":10.511104583740234},{"label":"STS","x":-41.98030090332031,"y":462.45440673828125,"id":"STS","clusterName":"Autos","attributes":{"Industry":"Autos","Centrality Measures":"","Closeness Centrality":"0.621","Harmonic Closeness Centrality":"0.695","Betweenness Centrality":"11.899","Eigenvector Centrality":"0.441","Other Measures":"","Degree":"16.0","Weighted Degree":"709.0","Eccentricity":"2.0"},"color":"rgb(255,131,255)","size":11.094783782958984},{"label":"NAV","x":662.00537109375,"y":-310.37420654296875,"id":"NAV","clusterName":"Autos","attributes":{"Industry":"Autos","Centrality Measures":"","Closeness Centrality":"0.0","Harmonic Closeness Centrality":"0.0","Betweenness Centrality":"0.0","Eigenvector Centrality":"0.0","Other Measures":"","Degree":"0.0","Weighted Degree":"0.0","Eccentricity":"0.0"},"color":"rgb(255,131,255)","size":10.0},{"label":"FSS","x":-670.63720703125,"y":201.13861083984375,"id":"FSS","clusterName":"Autos","attributes":{"Industry":"Autos","Centrality Measures":"","Closeness Centrality":"0.621","Harmonic Closeness Centrality":"0.695","Betweenness Centrality":"14.546","Eigenvector Centrality":"0.463","Other Measures":"","Degree":"16.0","Weighted Degree":"190.0","Eccentricity":"2.0"},"color":"rgb(255,131,255)","size":10.293383598327637},{"label":"MOD","x":-153.37738037109375,"y":-713.443359375,"id":"MOD","clusterName":"Autos","attributes":{"Industry":"Autos","Centrality Measures":"","Closeness Centrality":"0.0","Harmonic Closeness Centrality":"0.0","Betweenness Centrality":"0.0","Eigenvector Centrality":"0.0","Other Measures":"","Degree":"0.0","Weighted Degree":"0.0","Eccentricity":"0.0"},"color":"rgb(255,131,255)","size":10.0},{"label":"SMP","x":483.5773010253906,"y":116.1346664428711,"id":"SMP","clusterName":"Autos","attributes":{"Industry":"Autos","Centrality Measures":"","Closeness Centrality":"0.651","Harmonic Closeness Centrality":"0.732","Betweenness Centrality":"7.212","Eigenvector Centrality":"0.64","Other Measures":"","Degree":"19.0","Weighted Degree":"593.0","Eccentricity":"2.0"},"color":"rgb(255,131,255)","size":10.915664672851562},{"label":"DAN","x":-143.05105590820312,"y":-262.6195068359375,"id":"DAN","clusterName":"Autos","attributes":{"Industry":"Autos","Centrality Measures":"","Closeness Centrality":"0.788","Harmonic Closeness Centrality":"0.866","Betweenness Centrality":"22.108","Eigenvector Centrality":"0.953","Other Measures":"","Degree":"30.0","Weighted Degree":"1270.0","Eccentricity":"2.0"},"color":"rgb(255,131,255)","size":11.961036682128906},{"label":"HY","x":680.5642700195312,"y":156.98504638671875,"id":"HY","clusterName":"Autos","attributes":{"Industry":"Autos","Centrality Measures":"","Closeness Centrality":"0.603","Harmonic Closeness Centrality":"0.671","Betweenness Centrality":"3.643","Eigenvector Centrality":"0.448","Other Measures":"","Degree":"14.0","Weighted Degree":"199.0","Eccentricity":"2.0"},"color":"rgb(255,131,255)","size":10.307280540466309},{"label":"CTB","x":-520.1443481445312,"y":-442.3987121582031,"id":"CTB","clusterName":"Autos","attributes":{"Industry":"Autos","Centrality Measures":"","Closeness Centrality":"0.641","Harmonic Closeness Centrality":"0.72","Betweenness Centrality":"10.905","Eigenvector Centrality":"0.59","Other Measures":"","Degree":"18.0","Weighted Degree":"295.0","Eccentricity":"2.0"},"color":"rgb(255,131,255)","size":10.455516815185547},{"label":"GNTX","x":-436.10845947265625,"y":266.7910461425781,"id":"GNTX","clusterName":"Autos","attributes":{"Industry":"Autos","Centrality Measures":"","Closeness Centrality":"0.695","Harmonic Closeness Centrality":"0.78","Betweenness Centrality":"18.931","Eigenvector Centrality":"0.749","Other Measures":"","Degree":"23.0","Weighted Degree":"580.0","Eccentricity":"2.0"},"color":"rgb(255,131,255)","size":10.895591735839844},{"label":"FDML","x":-395.76300048828125,"y":539.658447265625,"id":"FDML","clusterName":"Autos","attributes":{"Industry":"Autos","Centrality Measures":"","Closeness Centrality":"0.612","Harmonic Closeness Centrality":"0.683","Betweenness Centrality":"5.746","Eigenvector Centrality":"0.515","Other Measures":"","Degree":"15.0","Weighted Degree":"306.0","Eccentricity":"2.0"},"color":"rgb(255,131,255)","size":10.472501754760742}],"edges":[{"source":"GT","target":"CAAS","id":"30221","attributes":{"sourceColor":"rgb(255,131,255)","targetColor":"rgb(255,131,255)"},"color":"rgb(255,131,255)","size":10.0},{"source":"CTB","target":"ALV","id":"30139","attributes":{"sourceColor":"rgb(255,131,255)","targetColor":"rgb(255,131,255)"},"color":"rgb(255,131,255)","size":4.0},{"source":"LCII","target":"THO","id":"30773","attributes":{"sourceColor":"rgb(255,131,255)","targetColor":"rgb(255,131,255)"},"color":"rgb(255,131,255)","size":119.0},{"source":"GNTX","target":"GM","id":"30385","attributes":{"sourceColor":"rgb(255,131,255)","targetColor":"rgb(255,131,255)"},"color":"rgb(255,131,255)","size":22.0},{"source":"TEN","target":"ALV","id":"30136","attributes":{"sourceColor":"rgb(255,131,255)","targetColor":"rgb(255,131,255)"},"color":"rgb(255,131,255)","size":50.0},{"source":"REVG","target":"TEX","id":"30752","attributes":{"sourceColor":"rgb(255,131,255)","targetColor":"rgb(255,131,255)"},"color":"rgb(255,131,255)","size":5.0},{"source":"STS","target":"SORL","id":"30620","attributes":{"sourceColor":"rgb(255,131,255)","targetColor":"rgb(255,131,255)"},"color":"rgb(255,131,255)","size":1.0},{"source":"GT","target":"AXL","id":"30175","attributes":{"sourceColor":"rgb(255,131,255)","targetColor":"rgb(255,131,255)"},"color":"rgb(255,131,255)","size":26.0},{"source":"PCAR","target":"LEA","id":"30503","attributes":{"sourceColor":"rgb(255,131,255)","targetColor":"rgb(255,131,255)"},"color":"rgb(255,131,255)","size":2.0},{"source":"SMP","target":"FSS","id":"30350","attributes":{"sourceColor":"rgb(255,131,255)","targetColor":"rgb(255,131,255)"},"color":"rgb(255,131,255)","size":8.0},{"source":"GM","target":"AXL","id":"30181","attributes":{"sourceColor":"rgb(255,131,255)","targetColor":"rgb(255,131,255)"},"color":"rgb(255,131,255)","size":58.0},{"source":"LCII","target":"GNTX","id":"30398","attributes":{"sourceColor":"rgb(255,131,255)","targetColor":"rgb(255,131,255)"},"color":"rgb(255,131,255)","size":3.0},{"source":"MTOR","target":"CPS","id":"30236","attributes":{"sourceColor":"rgb(255,131,255)","targetColor":"rgb(255,131,255)"},"color":"rgb(255,131,255)","size":26.0},{"source":"SMP","target":"DAN","id":"30273","attributes":{"sourceColor":"rgb(255,131,255)","targetColor":"rgb(255,131,255)"},"color":"rgb(255,131,255)","size":2.0},{"source":"SMP","target":"LEA","id":"30487","attributes":{"sourceColor":"rgb(255,131,255)","targetColor":"rgb(255,131,255)"},"color":"rgb(255,131,255)","size":2.0},{"source":"LEA","target":"CTB","id":"30255","attributes":{"sourceColor":"rgb(255,131,255)","targetColor":"rgb(255,131,255)"},"color":"rgb(255,131,255)","size":2.0},{"source":"CTB","target":"AXL","id":"30165","attributes":{"sourceColor":"rgb(255,131,255)","targetColor":"rgb(255,131,255)"},"color":"rgb(255,131,255)","size":10.0},{"source":"SORL","target":"BWA","id":"30218","attributes":{"sourceColor":"rgb(255,131,255)","targetColor":"rgb(255,131,255)"},"color":"rgb(255,131,255)","size":1.0},{"source":"SRI","target":"MTOR","id":"30539","attributes":{"sourceColor":"rgb(255,131,255)","targetColor":"rgb(255,131,255)"},"color":"rgb(255,131,255)","size":4.0},{"source":"TEN","target":"HAR","id":"30443","attributes":{"sourceColor":"rgb(255,131,255)","targetColor":"rgb(255,131,255)"},"color":"rgb(255,131,255)","size":24.0},{"source":"CVGI","target":"F","id":"30307","attributes":{"sourceColor":"rgb(255,131,255)","targetColor":"rgb(255,131,255)"},"color":"rgb(255,131,255)","size":1.0},{"source":"HY","target":"GM","id":"30378","attributes":{"sourceColor":"rgb(255,131,255)","targetColor":"rgb(255,131,255)"},"color":"rgb(255,131,255)","size":4.0},{"source":"VC","target":"GNTX","id":"30399","attributes":{"sourceColor":"rgb(255,131,255)","targetColor":"rgb(255,131,255)"},"color":"rgb(255,131,255)","size":10.0},{"source":"FDML","target":"CLC","id":"30230","attributes":{"sourceColor":"rgb(255,131,255)","targetColor":"rgb(255,131,255)"},"color":"rgb(255,131,255)","size":2.0},{"source":"KNDI","target":"CTB","id":"30264","attributes":{"sourceColor":"rgb(255,131,255)","targetColor":"rgb(255,131,255)"},"color":"rgb(255,131,255)","size":4.0},{"source":"LCII","target":"STS","id":"30694","attributes":{"sourceColor":"rgb(255,131,255)","targetColor":"rgb(255,131,255)"},"color":"rgb(255,131,255)","size":8.0},{"source":"WNC","target":"DAN","id":"30282","attributes":{"sourceColor":"rgb(255,131,255)","targetColor":"rgb(255,131,255)"},"color":"rgb(255,131,255)","size":2.0},{"source":"SPAR","target":"HY","id":"30454","attributes":{"sourceColor":"rgb(255,131,255)","targetColor":"rgb(255,131,255)"},"color":"rgb(255,131,255)","size":6.0},{"source":"GT","target":"GM","id":"30379","attributes":{"sourceColor":"rgb(255,131,255)","targetColor":"rgb(255,131,255)"},"color":"rgb(255,131,255)","size":235.0},{"source":"SMP","target":"HAR","id":"30436","attributes":{"sourceColor":"rgb(255,131,255)","targetColor":"rgb(255,131,255)"},"color":"rgb(255,131,255)","size":8.0},{"source":"DAN","target":"CTB","id":"30263","attributes":{"sourceColor":"rgb(255,131,255)","targetColor":"rgb(255,131,255)"},"color":"rgb(255,131,255)","size":6.0},{"source":"REVG","target":"HY","id":"30447","attributes":{"sourceColor":"rgb(255,131,255)","targetColor":"rgb(255,131,255)"},"color":"rgb(255,131,255)","size":2.0},{"source":"DAN","target":"BGG","id":"30188","attributes":{"sourceColor":"rgb(255,131,255)","targetColor":"rgb(255,131,255)"},"color":"rgb(255,131,255)","size":8.0},{"source":"PCAR","target":"GNTX","id":"30391","attributes":{"sourceColor":"rgb(255,131,255)","targetColor":"rgb(255,131,255)"},"color":"rgb(255,131,255)","size":21.0},{"source":"SPAR","target":"SMP","id":"30607","attributes":{"sourceColor":"rgb(255,131,255)","targetColor":"rgb(255,131,255)"},"color":"rgb(255,131,255)","size":2.0},{"source":"PII","target":"PCAR","id":"30560","attributes":{"sourceColor":"rgb(255,131,255)","targetColor":"rgb(255,131,255)"},"color":"rgb(255,131,255)","size":8.0},{"source":"WNC","target":"BWA","id":"30196","attributes":{"sourceColor":"rgb(255,131,255)","targetColor":"rgb(255,131,255)"},"color":"rgb(255,131,255)","size":2.0},{"source":"LEA","target":"GT","id":"30429","attributes":{"sourceColor":"rgb(255,131,255)","targetColor":"rgb(255,131,255)"},"color":"rgb(255,131,255)","size":83.0},{"source":"VC","target":"HAR","id":"30440","attributes":{"sourceColor":"rgb(255,131,255)","targetColor":"rgb(255,131,255)"},"color":"rgb(255,131,255)","size":28.0},{"source":"PII","target":"BWA","id":"30207","attributes":{"sourceColor":"rgb(255,131,255)","targetColor":"rgb(255,131,255)"},"color":"rgb(255,131,255)","size":13.0},{"source":"VC","target":"CAAS","id":"30223","attributes":{"sourceColor":"rgb(255,131,255)","targetColor":"rgb(255,131,255)"},"color":"rgb(255,131,255)","size":8.0},{"source":"SUP","target":"SMP","id":"30612","attributes":{"sourceColor":"rgb(255,131,255)","targetColor":"rgb(255,131,255)"},"color":"rgb(255,131,255)","size":4.0},{"source":"GNTX","target":"BGG","id":"30189","attributes":{"sourceColor":"rgb(255,131,255)","targetColor":"rgb(255,131,255)"},"color":"rgb(255,131,255)","size":2.0},{"source":"WBC","target":"GNTX","id":"30395","attributes":{"sourceColor":"rgb(255,131,255)","targetColor":"rgb(255,131,255)"},"color":"rgb(255,131,255)","size":26.0},{"source":"BWA","target":"BGG","id":"30185","attributes":{"sourceColor":"rgb(255,131,255)","targetColor":"rgb(255,131,255)"},"color":"rgb(255,131,255)","size":2.0},{"source":"WNC","target":"WGO","id":"30851","attributes":{"sourceColor":"rgb(255,131,255)","targetColor":"rgb(255,131,255)"},"color":"rgb(255,131,255)","size":4.0},{"source":"WBC","target":"MNTX","id":"30528","attributes":{"sourceColor":"rgb(255,131,255)","targetColor":"rgb(255,131,255)"},"color":"rgb(255,131,255)","size":1.0},{"source":"TEX","target":"LEA","id":"30500","attributes":{"sourceColor":"rgb(255,131,255)","targetColor":"rgb(255,131,255)"},"color":"rgb(255,131,255)","size":4.0},{"source":"WBC","target":"HY","id":"30448","attributes":{"sourceColor":"rgb(255,131,255)","targetColor":"rgb(255,131,255)"},"color":"rgb(255,131,255)","size":18.0},{"source":"SRI","target":"SMP","id":"30602","attributes":{"sourceColor":"rgb(255,131,255)","targetColor":"rgb(255,131,255)"},"color":"rgb(255,131,255)","size":4.0},{"source":"MTOR","target":"GM","id":"30368","attributes":{"sourceColor":"rgb(255,131,255)","targetColor":"rgb(255,131,255)"},"color":"rgb(255,131,255)","size":48.0},{"source":"MTOR","target":"HAR","id":"30438","attributes":{"sourceColor":"rgb(255,131,255)","targetColor":"rgb(255,131,255)"},"color":"rgb(255,131,255)","size":32.0},{"source":"SRI","target":"BWA","id":"30208","attributes":{"sourceColor":"rgb(255,131,255)","targetColor":"rgb(255,131,255)"},"color":"rgb(255,131,255)","size":50.0},{"source":"TEN","target":"AXL","id":"30162","attributes":{"sourceColor":"rgb(255,131,255)","targetColor":"rgb(255,131,255)"},"color":"rgb(255,131,255)","size":67.0},{"source":"LCII","target":"MLR","id":"30516","attributes":{"sourceColor":"rgb(255,131,255)","targetColor":"rgb(255,131,255)"},"color":"rgb(255,131,255)","size":2.0},{"source":"TEN","target":"BWA","id":"30211","attributes":{"sourceColor":"rgb(255,131,255)","targetColor":"rgb(255,131,255)"},"color":"rgb(255,131,255)","size":506.0},{"source":"REVG","target":"THO","id":"30783","attributes":{"sourceColor":"rgb(255,131,255)","targetColor":"rgb(255,131,255)"},"color":"rgb(255,131,255)","size":58.0},{"source":"STS","target":"SPAR","id":"30649","attributes":{"sourceColor":"rgb(255,131,255)","targetColor":"rgb(255,131,255)"},"color":"rgb(255,131,255)","size":2.0},{"source":"CVGI","target":"LEA","id":"30497","attributes":{"sourceColor":"rgb(255,131,255)","targetColor":"rgb(255,131,255)"},"color":"rgb(255,131,255)","size":1.0},{"source":"GT","target":"FSS","id":"30353","attributes":{"sourceColor":"rgb(255,131,255)","targetColor":"rgb(255,131,255)"},"color":"rgb(255,131,255)","size":2.0},{"source":"WBC","target":"PII","id":"30586","attributes":{"sourceColor":"rgb(255,131,255)","targetColor":"rgb(255,131,255)"},"color":"rgb(255,131,255)","size":18.0},{"source":"TEN","target":"SUP","id":"30717","attributes":{"sourceColor":"rgb(255,131,255)","targetColor":"rgb(255,131,255)"},"color":"rgb(255,131,255)","size":54.0},{"source":"SRI","target":"LEA","id":"30511","attributes":{"sourceColor":"rgb(255,131,255)","targetColor":"rgb(255,131,255)"},"color":"rgb(255,131,255)","size":20.0},{"source":"VC","target":"STRT","id":"30687","attributes":{"sourceColor":"rgb(255,131,255)","targetColor":"rgb(255,131,255)"},"color":"rgb(255,131,255)","size":2.0},{"source":"WGO","target":"LCII","id":"30476","attributes":{"sourceColor":"rgb(255,131,255)","targetColor":"rgb(255,131,255)"},"color":"rgb(255,131,255)","size":88.0},{"source":"SUP","target":"DAN","id":"30269","attributes":{"sourceColor":"rgb(255,131,255)","targetColor":"rgb(255,131,255)"},"color":"rgb(255,131,255)","size":24.0},{"source":"WNC","target":"GNTX","id":"30411","attributes":{"sourceColor":"rgb(255,131,255)","targetColor":"rgb(255,131,255)"},"color":"rgb(255,131,255)","size":4.0},{"source":"THO","target":"GM","id":"30373","attributes":{"sourceColor":"rgb(255,131,255)","targetColor":"rgb(255,131,255)"},"color":"rgb(255,131,255)","size":36.0},{"source":"PCAR","target":"KNDI","id":"30475","attributes":{"sourceColor":"rgb(255,131,255)","targetColor":"rgb(255,131,255)"},"color":"rgb(255,131,255)","size":4.0},{"source":"KNDI","target":"F","id":"30328","attributes":{"sourceColor":"rgb(255,131,255)","targetColor":"rgb(255,131,255)"},"color":"rgb(255,131,255)","size":119.0},{"source":"WBC","target":"MTOR","id":"30551","attributes":{"sourceColor":"rgb(255,131,255)","targetColor":"rgb(255,131,255)"},"color":"rgb(255,131,255)","size":48.0},{"source":"SUP","target":"LDL","id":"30481","attributes":{"sourceColor":"rgb(255,131,255)","targetColor":"rgb(255,131,255)"},"color":"rgb(255,131,255)","size":10.0},{"source":"MTOR","target":"LEA","id":"30494","attributes":{"sourceColor":"rgb(255,131,255)","targetColor":"rgb(255,131,255)"},"color":"rgb(255,131,255)","size":90.0},{"source":"WGO","target":"GT","id":"30424","attributes":{"sourceColor":"rgb(255,131,255)","targetColor":"rgb(255,131,255)"},"color":"rgb(255,131,255)","size":6.0},{"source":"STS","target":"SMP","id":"30606","attributes":{"sourceColor":"rgb(255,131,255)","targetColor":"rgb(255,131,255)"},"color":"rgb(255,131,255)","size":393.0},{"source":"WNC","target":"TEN","id":"30731","attributes":{"sourceColor":"rgb(255,131,255)","targetColor":"rgb(255,131,255)"},"color":"rgb(255,131,255)","size":2.0},{"source":"F","target":"DAN","id":"30279","attributes":{"sourceColor":"rgb(255,131,255)","targetColor":"rgb(255,131,255)"},"color":"rgb(255,131,255)","size":64.0},{"source":"SMP","target":"AXL","id":"30164","attributes":{"sourceColor":"rgb(255,131,255)","targetColor":"rgb(255,131,255)"},"color":"rgb(255,131,255)","size":2.0},{"source":"MTOR","target":"BWA","id":"30197","attributes":{"sourceColor":"rgb(255,131,255)","targetColor":"rgb(255,131,255)"},"color":"rgb(255,131,255)","size":55.0},{"source":"GM","target":"DAN","id":"30275","attributes":{"sourceColor":"rgb(255,131,255)","targetColor":"rgb(255,131,255)"},"color":"rgb(255,131,255)","size":63.0},{"source":"SMP","target":"GM","id":"30364","attributes":{"sourceColor":"rgb(255,131,255)","targetColor":"rgb(255,131,255)"},"color":"rgb(255,131,255)","size":2.0},{"source":"SPAR","target":"KNDI","id":"30467","attributes":{"sourceColor":"rgb(255,131,255)","targetColor":"rgb(255,131,255)"},"color":"rgb(255,131,255)","size":13.0},{"source":"DAN","target":"BWA","id":"30209","attributes":{"sourceColor":"rgb(255,131,255)","targetColor":"rgb(255,131,255)"},"color":"rgb(255,131,255)","size":193.0},{"source":"MLR","target":"CTB","id":"30258","attributes":{"sourceColor":"rgb(255,131,255)","targetColor":"rgb(255,131,255)"},"color":"rgb(255,131,255)","size":2.0},{"source":"TEX","target":"F","id":"30322","attributes":{"sourceColor":"rgb(255,131,255)","targetColor":"rgb(255,131,255)"},"color":"rgb(255,131,255)","size":2.0},{"source":"SMP","target":"F","id":"30325","attributes":{"sourceColor":"rgb(255,131,255)","targetColor":"rgb(255,131,255)"},"color":"rgb(255,131,255)","size":4.0},{"source":"WBC","target":"BWA","id":"30205","attributes":{"sourceColor":"rgb(255,131,255)","targetColor":"rgb(255,131,255)"},"color":"rgb(255,131,255)","size":8.0},{"source":"GNTX","target":"F","id":"30317","attributes":{"sourceColor":"rgb(255,131,255)","targetColor":"rgb(255,131,255)"},"color":"rgb(255,131,255)","size":45.0},{"source":"STRT","target":"FDML","id":"30340","attributes":{"sourceColor":"rgb(255,131,255)","targetColor":"rgb(255,131,255)"},"color":"rgb(255,131,255)","size":2.0},{"source":"HAR","target":"F","id":"30301","attributes":{"sourceColor":"rgb(255,131,255)","targetColor":"rgb(255,131,255)"},"color":"rgb(255,131,255)","size":4.0},{"source":"LEA","target":"HAR","id":"30439","attributes":{"sourceColor":"rgb(255,131,255)","targetColor":"rgb(255,131,255)"},"color":"rgb(255,131,255)","size":16.0},{"source":"WGO","target":"THO","id":"30779","attributes":{"sourceColor":"rgb(255,131,255)","targetColor":"rgb(255,131,255)"},"color":"rgb(255,131,255)","size":643.0},{"source":"STS","target":"SRI","id":"30660","attributes":{"sourceColor":"rgb(255,131,255)","targetColor":"rgb(255,131,255)"},"color":"rgb(255,131,255)","size":4.0},{"source":"CVGI","target":"FSS","id":"30359","attributes":{"sourceColor":"rgb(255,131,255)","targetColor":"rgb(255,131,255)"},"color":"rgb(255,131,255)","size":1.0},{"source":"SUP","target":"MTOR","id":"30533","attributes":{"sourceColor":"rgb(255,131,255)","targetColor":"rgb(255,131,255)"},"color":"rgb(255,131,255)","size":32.0},{"source":"WBC","target":"PCAR","id":"30575","attributes":{"sourceColor":"rgb(255,131,255)","targetColor":"rgb(255,131,255)"},"color":"rgb(255,131,255)","size":43.0},{"source":"MTOR","target":"KNDI","id":"30461","attributes":{"sourceColor":"rgb(255,131,255)","targetColor":"rgb(255,131,255)"},"color":"rgb(255,131,255)","size":11.0},{"source":"SRI","target":"HAR","id":"30434","attributes":{"sourceColor":"rgb(255,131,255)","targetColor":"rgb(255,131,255)"},"color":"rgb(255,131,255)","size":40.0},{"source":"PII","target":"KNDI","id":"30460","attributes":{"sourceColor":"rgb(255,131,255)","targetColor":"rgb(255,131,255)"},"color":"rgb(255,131,255)","size":4.0},{"source":"TEX","target":"GT","id":"30419","attributes":{"sourceColor":"rgb(255,131,255)","targetColor":"rgb(255,131,255)"},"color":"rgb(255,131,255)","size":14.0},{"source":"SUP","target":"LEA","id":"30492","attributes":{"sourceColor":"rgb(255,131,255)","targetColor":"rgb(255,131,255)"},"color":"rgb(255,131,255)","size":6.0},{"source":"VC","target":"ALV","id":"30150","attributes":{"sourceColor":"rgb(255,131,255)","targetColor":"rgb(255,131,255)"},"color":"rgb(255,131,255)","size":26.0},{"source":"MNTX","target":"CTB","id":"30261","attributes":{"sourceColor":"rgb(255,131,255)","targetColor":"rgb(255,131,255)"},"color":"rgb(255,131,255)","size":2.0},{"source":"PCAR","target":"F","id":"30312","attributes":{"sourceColor":"rgb(255,131,255)","targetColor":"rgb(255,131,255)"},"color":"rgb(255,131,255)","size":162.0},{"source":"THO","target":"PCAR","id":"30561","attributes":{"sourceColor":"rgb(255,131,255)","targetColor":"rgb(255,131,255)"},"color":"rgb(255,131,255)","size":12.0},{"source":"TEN","target":"GNTX","id":"30406","attributes":{"sourceColor":"rgb(255,131,255)","targetColor":"rgb(255,131,255)"},"color":"rgb(255,131,255)","size":27.0},{"source":"VC","target":"SUP","id":"30704","attributes":{"sourceColor":"rgb(255,131,255)","targetColor":"rgb(255,131,255)"},"color":"rgb(255,131,255)","size":34.0},{"source":"GT","target":"F","id":"30310","attributes":{"sourceColor":"rgb(255,131,255)","targetColor":"rgb(255,131,255)"},"color":"rgb(255,131,255)","size":284.0},{"source":"BGG","target":"AXL","id":"30163","attributes":{"sourceColor":"rgb(255,131,255)","targetColor":"rgb(255,131,255)"},"color":"rgb(255,131,255)","size":50.0},{"source":"LDL","target":"KNDI","id":"30474","attributes":{"sourceColor":"rgb(255,131,255)","targetColor":"rgb(255,131,255)"},"color":"rgb(255,131,255)","size":9.0},{"source":"TEX","target":"BWA","id":"30220","attributes":{"sourceColor":"rgb(255,131,255)","targetColor":"rgb(255,131,255)"},"color":"rgb(255,131,255)","size":2.0},{"source":"VC","target":"DAN","id":"30292","attributes":{"sourceColor":"rgb(255,131,255)","targetColor":"rgb(255,131,255)"},"color":"rgb(255,131,255)","size":31.0},{"source":"FSS","target":"DAN","id":"30293","attributes":{"sourceColor":"rgb(255,131,255)","targetColor":"rgb(255,131,255)"},"color":"rgb(255,131,255)","size":4.0},{"source":"SRI","target":"FDML","id":"30343","attributes":{"sourceColor":"rgb(255,131,255)","targetColor":"rgb(255,131,255)"},"color":"rgb(255,131,255)","size":52.0},{"source":"CVGI","target":"SORL","id":"30629","attributes":{"sourceColor":"rgb(255,131,255)","targetColor":"rgb(255,131,255)"},"color":"rgb(255,131,255)","size":2.0},{"source":"LCII","target":"BWA","id":"30212","attributes":{"sourceColor":"rgb(255,131,255)","targetColor":"rgb(255,131,255)"},"color":"rgb(255,131,255)","size":10.0},{"source":"PCAR","target":"MLR","id":"30520","attributes":{"sourceColor":"rgb(255,131,255)","targetColor":"rgb(255,131,255)"},"color":"rgb(255,131,255)","size":2.0},{"source":"VC","target":"MTOR","id":"30544","attributes":{"sourceColor":"rgb(255,131,255)","targetColor":"rgb(255,131,255)"},"color":"rgb(255,131,255)","size":42.0},{"source":"TEX","target":"MNTX","id":"30525","attributes":{"sourceColor":"rgb(255,131,255)","targetColor":"rgb(255,131,255)"},"color":"rgb(255,131,255)","size":17.0},{"source":"WNC","target":"STS","id":"30689","attributes":{"sourceColor":"rgb(255,131,255)","targetColor":"rgb(255,131,255)"},"color":"rgb(255,131,255)","size":86.0},{"source":"STS","target":"BGG","id":"30183","attributes":{"sourceColor":"rgb(255,131,255)","targetColor":"rgb(255,131,255)"},"color":"rgb(255,131,255)","size":2.0},{"source":"HAR","target":"ALV","id":"30160","attributes":{"sourceColor":"rgb(255,131,255)","targetColor":"rgb(255,131,255)"},"color":"rgb(255,131,255)","size":20.0},{"source":"WBC","target":"F","id":"30318","attributes":{"sourceColor":"rgb(255,131,255)","targetColor":"rgb(255,131,255)"},"color":"rgb(255,131,255)","size":2.0},{"source":"WGO","target":"PII","id":"30581","attributes":{"sourceColor":"rgb(255,131,255)","targetColor":"rgb(255,131,255)"},"color":"rgb(255,131,255)","size":111.0},{"source":"TEN","target":"GM","id":"30362","attributes":{"sourceColor":"rgb(255,131,255)","targetColor":"rgb(255,131,255)"},"color":"rgb(255,131,255)","size":61.0},{"source":"WGO","target":"BWA","id":"30210","attributes":{"sourceColor":"rgb(255,131,255)","targetColor":"rgb(255,131,255)"},"color":"rgb(255,131,255)","size":2.0},{"source":"STS","target":"PCAR","id":"30577","attributes":{"sourceColor":"rgb(255,131,255)","targetColor":"rgb(255,131,255)"},"color":"rgb(255,131,255)","size":2.0},{"source":"VC","target":"AXL","id":"30169","attributes":{"sourceColor":"rgb(255,131,255)","targetColor":"rgb(255,131,255)"},"color":"rgb(255,131,255)","size":20.0},{"source":"KNDI","target":"GM","id":"30375","attributes":{"sourceColor":"rgb(255,131,255)","targetColor":"rgb(255,131,255)"},"color":"rgb(255,131,255)","size":138.0},{"source":"TEX","target":"DAN","id":"30291","attributes":{"sourceColor":"rgb(255,131,255)","targetColor":"rgb(255,131,255)"},"color":"rgb(255,131,255)","size":8.0},{"source":"STRT","target":"F","id":"30297","attributes":{"sourceColor":"rgb(255,131,255)","targetColor":"rgb(255,131,255)"},"color":"rgb(255,131,255)","size":5.0},{"source":"STRT","target":"DAN","id":"30274","attributes":{"sourceColor":"rgb(255,131,255)","targetColor":"rgb(255,131,255)"},"color":"rgb(255,131,255)","size":2.0},{"source":"TEN","target":"DAN","id":"30285","attributes":{"sourceColor":"rgb(255,131,255)","targetColor":"rgb(255,131,255)"},"color":"rgb(255,131,255)","size":294.0},{"source":"MLR","target":"GNTX","id":"30390","attributes":{"sourceColor":"rgb(255,131,255)","targetColor":"rgb(255,131,255)"},"color":"rgb(255,131,255)","size":14.0},{"source":"MNTX","target":"HY","id":"30455","attributes":{"sourceColor":"rgb(255,131,255)","targetColor":"rgb(255,131,255)"},"color":"rgb(255,131,255)","size":2.0},{"source":"WBC","target":"FSS","id":"30346","attributes":{"sourceColor":"rgb(255,131,255)","targetColor":"rgb(255,131,255)"},"color":"rgb(255,131,255)","size":22.0},{"source":"WGO","target":"WBC","id":"30827","attributes":{"sourceColor":"rgb(255,131,255)","targetColor":"rgb(255,131,255)"},"color":"rgb(255,131,255)","size":40.0},{"source":"F","target":"CTB","id":"30262","attributes":{"sourceColor":"rgb(255,131,255)","targetColor":"rgb(255,131,255)"},"color":"rgb(255,131,255)","size":28.0},{"source":"HAR","target":"BWA","id":"30202","attributes":{"sourceColor":"rgb(255,131,255)","targetColor":"rgb(255,131,255)"},"color":"rgb(255,131,255)","size":16.0},{"source":"SORL","target":"F","id":"30323","attributes":{"sourceColor":"rgb(255,131,255)","targetColor":"rgb(255,131,255)"},"color":"rgb(255,131,255)","size":17.0},{"source":"SORL","target":"GM","id":"30374","attributes":{"sourceColor":"rgb(255,131,255)","targetColor":"rgb(255,131,255)"},"color":"rgb(255,131,255)","size":13.0},{"source":"FDML","target":"BWA","id":"30213","attributes":{"sourceColor":"rgb(255,131,255)","targetColor":"rgb(255,131,255)"},"color":"rgb(255,131,255)","size":14.0},{"source":"F","target":"BWA","id":"30204","attributes":{"sourceColor":"rgb(255,131,255)","targetColor":"rgb(255,131,255)"},"color":"rgb(255,131,255)","size":120.0},{"source":"THO","target":"GT","id":"30418","attributes":{"sourceColor":"rgb(255,131,255)","targetColor":"rgb(255,131,255)"},"color":"rgb(255,131,255)","size":12.0},{"source":"PCAR","target":"MTOR","id":"30546","attributes":{"sourceColor":"rgb(255,131,255)","targetColor":"rgb(255,131,255)"},"color":"rgb(255,131,255)","size":30.0},{"source":"TEX","target":"MTOR","id":"30556","attributes":{"sourceColor":"rgb(255,131,255)","targetColor":"rgb(255,131,255)"},"color":"rgb(255,131,255)","size":19.0},{"source":"TEN","target":"LEA","id":"30484","attributes":{"sourceColor":"rgb(255,131,255)","targetColor":"rgb(255,131,255)"},"color":"rgb(255,131,255)","size":89.0},{"source":"TEX","target":"FSS","id":"30348","attributes":{"sourceColor":"rgb(255,131,255)","targetColor":"rgb(255,131,255)"},"color":"rgb(255,131,255)","size":22.0},{"source":"VC","target":"CPS","id":"30240","attributes":{"sourceColor":"rgb(255,131,255)","targetColor":"rgb(255,131,255)"},"color":"rgb(255,131,255)","size":46.0},{"source":"STRT","target":"ALV","id":"30154","attributes":{"sourceColor":"rgb(255,131,255)","targetColor":"rgb(255,131,255)"},"color":"rgb(255,131,255)","size":2.0},{"source":"F","target":"AXL","id":"30170","attributes":{"sourceColor":"rgb(255,131,255)","targetColor":"rgb(255,131,255)"},"color":"rgb(255,131,255)","size":53.0},{"source":"THO","target":"F","id":"30311","attributes":{"sourceColor":"rgb(255,131,255)","targetColor":"rgb(255,131,255)"},"color":"rgb(255,131,255)","size":37.0},{"source":"GNTX","target":"AXL","id":"30180","attributes":{"sourceColor":"rgb(255,131,255)","targetColor":"rgb(255,131,255)"},"color":"rgb(255,131,255)","size":46.0},{"source":"PCAR","target":"CTB","id":"30257","attributes":{"sourceColor":"rgb(255,131,255)","targetColor":"rgb(255,131,255)"},"color":"rgb(255,131,255)","size":16.0},{"source":"THO","target":"CTB","id":"30259","attributes":{"sourceColor":"rgb(255,131,255)","targetColor":"rgb(255,131,255)"},"color":"rgb(255,131,255)","size":2.0},{"source":"REVG","target":"LEA","id":"30510","attributes":{"sourceColor":"rgb(255,131,255)","targetColor":"rgb(255,131,255)"},"color":"rgb(255,131,255)","size":1.0},{"source":"VC","target":"SRI","id":"30659","attributes":{"sourceColor":"rgb(255,131,255)","targetColor":"rgb(255,131,255)"},"color":"rgb(255,131,255)","size":34.0},{"source":"CTB","target":"CPS","id":"30235","attributes":{"sourceColor":"rgb(255,131,255)","targetColor":"rgb(255,131,255)"},"color":"rgb(255,131,255)","size":30.0},{"source":"SPAR","target":"BGG","id":"30191","attributes":{"sourceColor":"rgb(255,131,255)","targetColor":"rgb(255,131,255)"},"color":"rgb(255,131,255)","size":101.0},{"source":"GNTX","target":"CPS","id":"30238","attributes":{"sourceColor":"rgb(255,131,255)","targetColor":"rgb(255,131,255)"},"color":"rgb(255,131,255)","size":2.0},{"source":"THO","target":"LEA","id":"30491","attributes":{"sourceColor":"rgb(255,131,255)","targetColor":"rgb(255,131,255)"},"color":"rgb(255,131,255)","size":9.0},{"source":"MTOR","target":"GT","id":"30413","attributes":{"sourceColor":"rgb(255,131,255)","targetColor":"rgb(255,131,255)"},"color":"rgb(255,131,255)","size":2.0},{"source":"PCAR","target":"GM","id":"30361","attributes":{"sourceColor":"rgb(255,131,255)","targetColor":"rgb(255,131,255)"},"color":"rgb(255,131,255)","size":39.0},{"source":"SORL","target":"SMP","id":"30618","attributes":{"sourceColor":"rgb(255,131,255)","targetColor":"rgb(255,131,255)"},"color":"rgb(255,131,255)","size":10.0},{"source":"VC","target":"BWA","id":"30219","attributes":{"sourceColor":"rgb(255,131,255)","targetColor":"rgb(255,131,255)"},"color":"rgb(255,131,255)","size":67.0},{"source":"SRI","target":"CPS","id":"30245","attributes":{"sourceColor":"rgb(255,131,255)","targetColor":"rgb(255,131,255)"},"color":"rgb(255,131,255)","size":11.0},{"source":"GT","target":"ALV","id":"30143","attributes":{"sourceColor":"rgb(255,131,255)","targetColor":"rgb(255,131,255)"},"color":"rgb(255,131,255)","size":14.0},{"source":"CVGI","target":"VC","id":"30808","attributes":{"sourceColor":"rgb(255,131,255)","targetColor":"rgb(255,131,255)"},"color":"rgb(255,131,255)","size":2.0},{"source":"FSS","target":"ALV","id":"30151","attributes":{"sourceColor":"rgb(255,131,255)","targetColor":"rgb(255,131,255)"},"color":"rgb(255,131,255)","size":4.0},{"source":"WGO","target":"STRT","id":"30683","attributes":{"sourceColor":"rgb(255,131,255)","targetColor":"rgb(255,131,255)"},"color":"rgb(255,131,255)","size":15.0},{"source":"STRT","target":"AXL","id":"30168","attributes":{"sourceColor":"rgb(255,131,255)","targetColor":"rgb(255,131,255)"},"color":"rgb(255,131,255)","size":102.0},{"source":"LCII","target":"GM","id":"30383","attributes":{"sourceColor":"rgb(255,131,255)","targetColor":"rgb(255,131,255)"},"color":"rgb(255,131,255)","size":1.0},{"source":"MTOR","target":"FSS","id":"30357","attributes":{"sourceColor":"rgb(255,131,255)","targetColor":"rgb(255,131,255)"},"color":"rgb(255,131,255)","size":2.0},{"source":"VC","target":"GM","id":"30387","attributes":{"sourceColor":"rgb(255,131,255)","targetColor":"rgb(255,131,255)"},"color":"rgb(255,131,255)","size":40.0},{"source":"PII","target":"DAN","id":"30287","attributes":{"sourceColor":"rgb(255,131,255)","targetColor":"rgb(255,131,255)"},"color":"rgb(255,131,255)","size":4.0},{"source":"GM","target":"ALV","id":"30138","attributes":{"sourceColor":"rgb(255,131,255)","targetColor":"rgb(255,131,255)"},"color":"rgb(255,131,255)","size":68.0},{"source":"WNC","target":"SPAR","id":"30643","attributes":{"sourceColor":"rgb(255,131,255)","targetColor":"rgb(255,131,255)"},"color":"rgb(255,131,255)","size":43.0},{"source":"REVG","target":"GM","id":"30366","attributes":{"sourceColor":"rgb(255,131,255)","targetColor":"rgb(255,131,255)"},"color":"rgb(255,131,255)","size":55.0},{"source":"SPAR","target":"PCAR","id":"30569","attributes":{"sourceColor":"rgb(255,131,255)","targetColor":"rgb(255,131,255)"},"color":"rgb(255,131,255)","size":4.0},{"source":"FDML","target":"F","id":"30314","attributes":{"sourceColor":"rgb(255,131,255)","targetColor":"rgb(255,131,255)"},"color":"rgb(255,131,255)","size":4.0},{"source":"SORL","target":"KNDI","id":"30469","attributes":{"sourceColor":"rgb(255,131,255)","targetColor":"rgb(255,131,255)"},"color":"rgb(255,131,255)","size":62.0},{"source":"SUP","target":"FDML","id":"30333","attributes":{"sourceColor":"rgb(255,131,255)","targetColor":"rgb(255,131,255)"},"color":"rgb(255,131,255)","size":10.0},{"source":"HAR","target":"CPS","id":"30237","attributes":{"sourceColor":"rgb(255,131,255)","targetColor":"rgb(255,131,255)"},"color":"rgb(255,131,255)","size":18.0},{"source":"GT","target":"DAN","id":"30271","attributes":{"sourceColor":"rgb(255,131,255)","targetColor":"rgb(255,131,255)"},"color":"rgb(255,131,255)","size":16.0},{"source":"SUP","target":"SPAR","id":"30646","attributes":{"sourceColor":"rgb(255,131,255)","targetColor":"rgb(255,131,255)"},"color":"rgb(255,131,255)","size":10.0},{"source":"WBC","target":"LEA","id":"30506","attributes":{"sourceColor":"rgb(255,131,255)","targetColor":"rgb(255,131,255)"},"color":"rgb(255,131,255)","size":24.0},{"source":"STS","target":"STRT","id":"30681","attributes":{"sourceColor":"rgb(255,131,255)","targetColor":"rgb(255,131,255)"},"color":"rgb(255,131,255)","size":4.0},{"source":"PII","target":"FSS","id":"30358","attributes":{"sourceColor":"rgb(255,131,255)","targetColor":"rgb(255,131,255)"},"color":"rgb(255,131,255)","size":4.0},{"source":"BWA","target":"AXL","id":"30166","attributes":{"sourceColor":"rgb(255,131,255)","targetColor":"rgb(255,131,255)"},"color":"rgb(255,131,255)","size":82.0},{"source":"LCII","target":"LEA","id":"30501","attributes":{"sourceColor":"rgb(255,131,255)","targetColor":"rgb(255,131,255)"},"color":"rgb(255,131,255)","size":4.0},{"source":"TEN","target":"F","id":"30308","attributes":{"sourceColor":"rgb(255,131,255)","targetColor":"rgb(255,131,255)"},"color":"rgb(255,131,255)","size":53.0},{"source":"F","target":"CPS","id":"30246","attributes":{"sourceColor":"rgb(255,131,255)","targetColor":"rgb(255,131,255)"},"color":"rgb(255,131,255)","size":8.0},{"source":"GM","target":"FSS","id":"30354","attributes":{"sourceColor":"rgb(255,131,255)","targetColor":"rgb(255,131,255)"},"color":"rgb(255,131,255)","size":2.0},{"source":"TEX","target":"LDL","id":"30479","attributes":{"sourceColor":"rgb(255,131,255)","targetColor":"rgb(255,131,255)"},"color":"rgb(255,131,255)","size":2.0},{"source":"SRI","target":"KNDI","id":"30470","attributes":{"sourceColor":"rgb(255,131,255)","targetColor":"rgb(255,131,255)"},"color":"rgb(255,131,255)","size":1.0},{"source":"HY","target":"AXL","id":"30179","attributes":{"sourceColor":"rgb(255,131,255)","targetColor":"rgb(255,131,255)"},"color":"rgb(255,131,255)","size":5.0},{"source":"KNDI","target":"BWA","id":"30201","attributes":{"sourceColor":"rgb(255,131,255)","targetColor":"rgb(255,131,255)"},"color":"rgb(255,131,255)","size":2.0},{"source":"SMP","target":"BWA","id":"30217","attributes":{"sourceColor":"rgb(255,131,255)","targetColor":"rgb(255,131,255)"},"color":"rgb(255,131,255)","size":2.0},{"source":"THO","target":"DAN","id":"30286","attributes":{"sourceColor":"rgb(255,131,255)","targetColor":"rgb(255,131,255)"},"color":"rgb(255,131,255)","size":14.0},{"source":"SRI","target":"SORL","id":"30634","attributes":{"sourceColor":"rgb(255,131,255)","targetColor":"rgb(255,131,255)"},"color":"rgb(255,131,255)","size":2.0},{"source":"WNC","target":"MLR","id":"30514","attributes":{"sourceColor":"rgb(255,131,255)","targetColor":"rgb(255,131,255)"},"color":"rgb(255,131,255)","size":2.0},{"source":"HAR","target":"DAN","id":"30289","attributes":{"sourceColor":"rgb(255,131,255)","targetColor":"rgb(255,131,255)"},"color":"rgb(255,131,255)","size":26.0},{"source":"GM","target":"CPS","id":"30234","attributes":{"sourceColor":"rgb(255,131,255)","targetColor":"rgb(255,131,255)"},"color":"rgb(255,131,255)","size":2.0},{"source":"LEA","target":"GM","id":"30386","attributes":{"sourceColor":"rgb(255,131,255)","targetColor":"rgb(255,131,255)"},"color":"rgb(255,131,255)","size":159.0},{"source":"MTOR","target":"AXL","id":"30167","attributes":{"sourceColor":"rgb(255,131,255)","targetColor":"rgb(255,131,255)"},"color":"rgb(255,131,255)","size":12.0},{"source":"LEA","target":"ALV","id":"30146","attributes":{"sourceColor":"rgb(255,131,255)","targetColor":"rgb(255,131,255)"},"color":"rgb(255,131,255)","size":108.0},{"source":"LEA","target":"BWA","id":"30214","attributes":{"sourceColor":"rgb(255,131,255)","targetColor":"rgb(255,131,255)"},"color":"rgb(255,131,255)","size":219.0},{"source":"GNTX","target":"CLC","id":"30229","attributes":{"sourceColor":"rgb(255,131,255)","targetColor":"rgb(255,131,255)"},"color":"rgb(255,131,255)","size":2.0},{"source":"WBC","target":"DAN","id":"30294","attributes":{"sourceColor":"rgb(255,131,255)","targetColor":"rgb(255,131,255)"},"color":"rgb(255,131,255)","size":22.0},{"source":"VC","target":"TEX","id":"30759","attributes":{"sourceColor":"rgb(255,131,255)","targetColor":"rgb(255,131,255)"},"color":"rgb(255,131,255)","size":5.0},{"source":"REVG","target":"KNDI","id":"30471","attributes":{"sourceColor":"rgb(255,131,255)","targetColor":"rgb(255,131,255)"},"color":"rgb(255,131,255)","size":1.0},{"source":"TEX","target":"SPAR","id":"30642","attributes":{"sourceColor":"rgb(255,131,255)","targetColor":"rgb(255,131,255)"},"color":"rgb(255,131,255)","size":2.0},{"source":"SORL","target":"MTOR","id":"30541","attributes":{"sourceColor":"rgb(255,131,255)","targetColor":"rgb(255,131,255)"},"color":"rgb(255,131,255)","size":11.0},{"source":"SORL","target":"ALV","id":"30152","attributes":{"sourceColor":"rgb(255,131,255)","targetColor":"rgb(255,131,255)"},"color":"rgb(255,131,255)","size":3.0},{"source":"MNTX","target":"LEA","id":"30482","attributes":{"sourceColor":"rgb(255,131,255)","targetColor":"rgb(255,131,255)"},"color":"rgb(255,131,255)","size":2.0},{"source":"LEA","target":"HY","id":"30456","attributes":{"sourceColor":"rgb(255,131,255)","targetColor":"rgb(255,131,255)"},"color":"rgb(255,131,255)","size":2.0},{"source":"MLR","target":"FSS","id":"30347","attributes":{"sourceColor":"rgb(255,131,255)","targetColor":"rgb(255,131,255)"},"color":"rgb(255,131,255)","size":5.0},{"source":"VC","target":"FDML","id":"30335","attributes":{"sourceColor":"rgb(255,131,255)","targetColor":"rgb(255,131,255)"},"color":"rgb(255,131,255)","size":18.0},{"source":"TEN","target":"SRI","id":"30656","attributes":{"sourceColor":"rgb(255,131,255)","targetColor":"rgb(255,131,255)"},"color":"rgb(255,131,255)","size":26.0},{"source":"FDML","target":"ALV","id":"30142","attributes":{"sourceColor":"rgb(255,131,255)","targetColor":"rgb(255,131,255)"},"color":"rgb(255,131,255)","size":18.0},{"source":"SUP","target":"BWA","id":"30206","attributes":{"sourceColor":"rgb(255,131,255)","targetColor":"rgb(255,131,255)"},"color":"rgb(255,131,255)","size":6.0},{"source":"SUP","target":"F","id":"30329","attributes":{"sourceColor":"rgb(255,131,255)","targetColor":"rgb(255,131,255)"},"color":"rgb(255,131,255)","size":2.0},{"source":"CVGI","target":"MLR","id":"30513","attributes":{"sourceColor":"rgb(255,131,255)","targetColor":"rgb(255,131,255)"},"color":"rgb(255,131,255)","size":1.0},{"source":"GT","target":"CTB","id":"30252","attributes":{"sourceColor":"rgb(255,131,255)","targetColor":"rgb(255,131,255)"},"color":"rgb(255,131,255)","size":153.0},{"source":"WGO","target":"MTOR","id":"30545","attributes":{"sourceColor":"rgb(255,131,255)","targetColor":"rgb(255,131,255)"},"color":"rgb(255,131,255)","size":22.0},{"source":"LEA","target":"DAN","id":"30268","attributes":{"sourceColor":"rgb(255,131,255)","targetColor":"rgb(255,131,255)"},"color":"rgb(255,131,255)","size":144.0},{"source":"VC","target":"F","id":"30327","attributes":{"sourceColor":"rgb(255,131,255)","targetColor":"rgb(255,131,255)"},"color":"rgb(255,131,255)","size":43.0},{"source":"MTOR","target":"GNTX","id":"30400","attributes":{"sourceColor":"rgb(255,131,255)","targetColor":"rgb(255,131,255)"},"color":"rgb(255,131,255)","size":2.0},{"source":"REVG","target":"MTOR","id":"30552","attributes":{"sourceColor":"rgb(255,131,255)","targetColor":"rgb(255,131,255)"},"color":"rgb(255,131,255)","size":3.0},{"source":"GNTX","target":"BWA","id":"30194","attributes":{"sourceColor":"rgb(255,131,255)","targetColor":"rgb(255,131,255)"},"color":"rgb(255,131,255)","size":32.0},{"source":"PII","target":"GM","id":"30369","attributes":{"sourceColor":"rgb(255,131,255)","targetColor":"rgb(255,131,255)"},"color":"rgb(255,131,255)","size":489.0},{"source":"SPAR","target":"GT","id":"30415","attributes":{"sourceColor":"rgb(255,131,255)","targetColor":"rgb(255,131,255)"},"color":"rgb(255,131,255)","size":240.0},{"source":"REVG","target":"SPAR","id":"30650","attributes":{"sourceColor":"rgb(255,131,255)","targetColor":"rgb(255,131,255)"},"color":"rgb(255,131,255)","size":2.0},{"source":"WGO","target":"F","id":"30319","attributes":{"sourceColor":"rgb(255,131,255)","targetColor":"rgb(255,131,255)"},"color":"rgb(255,131,255)","size":37.0},{"source":"BWA","target":"ALV","id":"30148","attributes":{"sourceColor":"rgb(255,131,255)","targetColor":"rgb(255,131,255)"},"color":"rgb(255,131,255)","size":63.0},{"source":"MNTX","target":"LDL","id":"30478","attributes":{"sourceColor":"rgb(255,131,255)","targetColor":"rgb(255,131,255)"},"color":"rgb(255,131,255)","size":18.0},{"source":"TEN","target":"CTB","id":"30254","attributes":{"sourceColor":"rgb(255,131,255)","targetColor":"rgb(255,131,255)"},"color":"rgb(255,131,255)","size":2.0},{"source":"HAR","target":"CLC","id":"30231","attributes":{"sourceColor":"rgb(255,131,255)","targetColor":"rgb(255,131,255)"},"color":"rgb(255,131,255)","size":20.0},{"source":"PII","target":"F","id":"30299","attributes":{"sourceColor":"rgb(255,131,255)","targetColor":"rgb(255,131,255)"},"color":"rgb(255,131,255)","size":34.0},{"source":"SMP","target":"MTOR","id":"30559","attributes":{"sourceColor":"rgb(255,131,255)","targetColor":"rgb(255,131,255)"},"color":"rgb(255,131,255)","size":14.0},{"source":"SMP","target":"ALV","id":"30153","attributes":{"sourceColor":"rgb(255,131,255)","targetColor":"rgb(255,131,255)"},"color":"rgb(255,131,255)","size":8.0},{"source":"REVG","target":"F","id":"30298","attributes":{"sourceColor":"rgb(255,131,255)","targetColor":"rgb(255,131,255)"},"color":"rgb(255,131,255)","size":62.0},{"source":"VC","target":"SORL","id":"30633","attributes":{"sourceColor":"rgb(255,131,255)","targetColor":"rgb(255,131,255)"},"color":"rgb(255,131,255)","size":2.0},{"source":"STRT","target":"MLR","id":"30519","attributes":{"sourceColor":"rgb(255,131,255)","targetColor":"rgb(255,131,255)"},"color":"rgb(255,131,255)","size":6.0},{"source":"THO","target":"MTOR","id":"30543","attributes":{"sourceColor":"rgb(255,131,255)","targetColor":"rgb(255,131,255)"},"color":"rgb(255,131,255)","size":2.0},{"source":"F","target":"ALV","id":"30147","attributes":{"sourceColor":"rgb(255,131,255)","targetColor":"rgb(255,131,255)"},"color":"rgb(255,131,255)","size":78.0},{"source":"STRT","target":"CPS","id":"30248","attributes":{"sourceColor":"rgb(255,131,255)","targetColor":"rgb(255,131,255)"},"color":"rgb(255,131,255)","size":6.0},{"source":"SORL","target":"DAN","id":"30290","attributes":{"sourceColor":"rgb(255,131,255)","targetColor":"rgb(255,131,255)"},"color":"rgb(255,131,255)","size":6.0},{"source":"WBC","target":"SRI","id":"30666","attributes":{"sourceColor":"rgb(255,131,255)","targetColor":"rgb(255,131,255)"},"color":"rgb(255,131,255)","size":6.0},{"source":"PII","target":"ALV","id":"30149","attributes":{"sourceColor":"rgb(255,131,255)","targetColor":"rgb(255,131,255)"},"color":"rgb(255,131,255)","size":24.0},{"source":"CVGI","target":"STS","id":"30700","attributes":{"sourceColor":"rgb(255,131,255)","targetColor":"rgb(255,131,255)"},"color":"rgb(255,131,255)","size":189.0},{"source":"GM","target":"CLC","id":"30232","attributes":{"sourceColor":"rgb(255,131,255)","targetColor":"rgb(255,131,255)"},"color":"rgb(255,131,255)","size":31.0},{"source":"STS","target":"LEA","id":"30486","attributes":{"sourceColor":"rgb(255,131,255)","targetColor":"rgb(255,131,255)"},"color":"rgb(255,131,255)","size":2.0},{"source":"SRI","target":"ALV","id":"30137","attributes":{"sourceColor":"rgb(255,131,255)","targetColor":"rgb(255,131,255)"},"color":"rgb(255,131,255)","size":16.0},{"source":"LEA","target":"F","id":"30305","attributes":{"sourceColor":"rgb(255,131,255)","targetColor":"rgb(255,131,255)"},"color":"rgb(255,131,255)","size":170.0},{"source":"SUP","target":"AXL","id":"30174","attributes":{"sourceColor":"rgb(255,131,255)","targetColor":"rgb(255,131,255)"},"color":"rgb(255,131,255)","size":4.0},{"source":"WBC","target":"GM","id":"30370","attributes":{"sourceColor":"rgb(255,131,255)","targetColor":"rgb(255,131,255)"},"color":"rgb(255,131,255)","size":17.0},{"source":"PCAR","target":"DAN","id":"30295","attributes":{"sourceColor":"rgb(255,131,255)","targetColor":"rgb(255,131,255)"},"color":"rgb(255,131,255)","size":26.0},{"source":"MTOR","target":"ALV","id":"30144","attributes":{"sourceColor":"rgb(255,131,255)","targetColor":"rgb(255,131,255)"},"color":"rgb(255,131,255)","size":16.0},{"source":"MTOR","target":"DAN","id":"30278","attributes":{"sourceColor":"rgb(255,131,255)","targetColor":"rgb(255,131,255)"},"color":"rgb(255,131,255)","size":67.0},{"source":"VC","target":"SMP","id":"30617","attributes":{"sourceColor":"rgb(255,131,255)","targetColor":"rgb(255,131,255)"},"color":"rgb(255,131,255)","size":2.0},{"source":"F","target":"BGG","id":"30186","attributes":{"sourceColor":"rgb(255,131,255)","targetColor":"rgb(255,131,255)"},"color":"rgb(255,131,255)","size":4.0},{"source":"CPS","target":"BWA","id":"30195","attributes":{"sourceColor":"rgb(255,131,255)","targetColor":"rgb(255,131,255)"},"color":"rgb(255,131,255)","size":34.0},{"source":"SORL","target":"GT","id":"30425","attributes":{"sourceColor":"rgb(255,131,255)","targetColor":"rgb(255,131,255)"},"color":"rgb(255,131,255)","size":10.0},{"source":"VC","target":"LEA","id":"30496","attributes":{"sourceColor":"rgb(255,131,255)","targetColor":"rgb(255,131,255)"},"color":"rgb(255,131,255)","size":163.0},{"source":"CVGI","target":"SMP","id":"30604","attributes":{"sourceColor":"rgb(255,131,255)","targetColor":"rgb(255,131,255)"},"color":"rgb(255,131,255)","size":120.0},{"source":"GNTX","target":"CTB","id":"30256","attributes":{"sourceColor":"rgb(255,131,255)","targetColor":"rgb(255,131,255)"},"color":"rgb(255,131,255)","size":4.0},{"source":"TEX","target":"PCAR","id":"30562","attributes":{"sourceColor":"rgb(255,131,255)","targetColor":"rgb(255,131,255)"},"color":"rgb(255,131,255)","size":107.0},{"source":"THO","target":"PII","id":"30594","attributes":{"sourceColor":"rgb(255,131,255)","targetColor":"rgb(255,131,255)"},"color":"rgb(255,131,255)","size":93.0},{"source":"FDML","target":"AXL","id":"30182","attributes":{"sourceColor":"rgb(255,131,255)","targetColor":"rgb(255,131,255)"},"color":"rgb(255,131,255)","size":10.0},{"source":"WGO","target":"SUP","id":"30715","attributes":{"sourceColor":"rgb(255,131,255)","targetColor":"rgb(255,131,255)"},"color":"rgb(255,131,255)","size":2.0},{"source":"MNTX","target":"SPAR","id":"30639","attributes":{"sourceColor":"rgb(255,131,255)","targetColor":"rgb(255,131,255)"},"color":"rgb(255,131,255)","size":1.0},{"source":"MTOR","target":"FDML","id":"30332","attributes":{"sourceColor":"rgb(255,131,255)","targetColor":"rgb(255,131,255)"},"color":"rgb(255,131,255)","size":20.0},{"source":"SRI","target":"AXL","id":"30173","attributes":{"sourceColor":"rgb(255,131,255)","targetColor":"rgb(255,131,255)"},"color":"rgb(255,131,255)","size":6.0},{"source":"TEN","target":"STS","id":"30696","attributes":{"sourceColor":"rgb(255,131,255)","targetColor":"rgb(255,131,255)"},"color":"rgb(255,131,255)","size":8.0},{"source":"KNDI","target":"CAAS","id":"30222","attributes":{"sourceColor":"rgb(255,131,255)","targetColor":"rgb(255,131,255)"},"color":"rgb(255,131,255)","size":6.0},{"source":"GM","target":"CTB","id":"30249","attributes":{"sourceColor":"rgb(255,131,255)","targetColor":"rgb(255,131,255)"},"color":"rgb(255,131,255)","size":12.0},{"source":"SUP","target":"GNTX","id":"30393","attributes":{"sourceColor":"rgb(255,131,255)","targetColor":"rgb(255,131,255)"},"color":"rgb(255,131,255)","size":6.0},{"source":"DAN","target":"ALV","id":"30145","attributes":{"sourceColor":"rgb(255,131,255)","targetColor":"rgb(255,131,255)"},"color":"rgb(255,131,255)","size":49.0},{"source":"STRT","target":"GM","id":"30371","attributes":{"sourceColor":"rgb(255,131,255)","targetColor":"rgb(255,131,255)"},"color":"rgb(255,131,255)","size":2.0},{"source":"FSS","target":"CLC","id":"30228","attributes":{"sourceColor":"rgb(255,131,255)","targetColor":"rgb(255,131,255)"},"color":"rgb(255,131,255)","size":28.0},{"source":"TEN","target":"CPS","id":"30242","attributes":{"sourceColor":"rgb(255,131,255)","targetColor":"rgb(255,131,255)"},"color":"rgb(255,131,255)","size":36.0},{"source":"LEA","target":"CPS","id":"30241","attributes":{"sourceColor":"rgb(255,131,255)","targetColor":"rgb(255,131,255)"},"color":"rgb(255,131,255)","size":40.0},{"source":"WGO","target":"PCAR","id":"30579","attributes":{"sourceColor":"rgb(255,131,255)","targetColor":"rgb(255,131,255)"},"color":"rgb(255,131,255)","size":3.0},{"source":"MTOR","target":"F","id":"30320","attributes":{"sourceColor":"rgb(255,131,255)","targetColor":"rgb(255,131,255)"},"color":"rgb(255,131,255)","size":83.0},{"source":"GNTX","target":"DAN","id":"30272","attributes":{"sourceColor":"rgb(255,131,255)","targetColor":"rgb(255,131,255)"},"color":"rgb(255,131,255)","size":14.0},{"source":"VC","target":"TEN","id":"30740","attributes":{"sourceColor":"rgb(255,131,255)","targetColor":"rgb(255,131,255)"},"color":"rgb(255,131,255)","size":40.0},{"source":"WBC","target":"AXL","id":"30172","attributes":{"sourceColor":"rgb(255,131,255)","targetColor":"rgb(255,131,255)"},"color":"rgb(255,131,255)","size":2.0},{"source":"VC","target":"PII","id":"30598","attributes":{"sourceColor":"rgb(255,131,255)","targetColor":"rgb(255,131,255)"},"color":"rgb(255,131,255)","size":2.0},{"source":"SPAR","target":"F","id":"30304","attributes":{"sourceColor":"rgb(255,131,255)","targetColor":"rgb(255,131,255)"},"color":"rgb(255,131,255)","size":159.0},{"source":"DAN","target":"AXL","id":"30161","attributes":{"sourceColor":"rgb(255,131,255)","targetColor":"rgb(255,131,255)"},"color":"rgb(255,131,255)","size":62.0},{"source":"TEN","target":"SMP","id":"30614","attributes":{"sourceColor":"rgb(255,131,255)","targetColor":"rgb(255,131,255)"},"color":"rgb(255,131,255)","size":4.0},{"source":"REVG","target":"WBC","id":"30819","attributes":{"sourceColor":"rgb(255,131,255)","targetColor":"rgb(255,131,255)"},"color":"rgb(255,131,255)","size":1.0},{"source":"WNC","target":"GT","id":"30431","attributes":{"sourceColor":"rgb(255,131,255)","targetColor":"rgb(255,131,255)"},"color":"rgb(255,131,255)","size":67.0},{"source":"THO","target":"MNTX","id":"30527","attributes":{"sourceColor":"rgb(255,131,255)","targetColor":"rgb(255,131,255)"},"color":"rgb(255,131,255)","size":12.0},{"source":"STS","target":"FSS","id":"30352","attributes":{"sourceColor":"rgb(255,131,255)","targetColor":"rgb(255,131,255)"},"color":"rgb(255,131,255)","size":2.0},{"source":"WBC","target":"TEX","id":"30766","attributes":{"sourceColor":"rgb(255,131,255)","targetColor":"rgb(255,131,255)"},"color":"rgb(255,131,255)","size":32.0},{"source":"LCII","target":"PCAR","id":"30580","attributes":{"sourceColor":"rgb(255,131,255)","targetColor":"rgb(255,131,255)"},"color":"rgb(255,131,255)","size":14.0},{"source":"THO","target":"CAAS","id":"30226","attributes":{"sourceColor":"rgb(255,131,255)","targetColor":"rgb(255,131,255)"},"color":"rgb(255,131,255)","size":4.0},{"source":"WBC","target":"ALV","id":"30159","attributes":{"sourceColor":"rgb(255,131,255)","targetColor":"rgb(255,131,255)"},"color":"rgb(255,131,255)","size":16.0},{"source":"GT","target":"BWA","id":"30215","attributes":{"sourceColor":"rgb(255,131,255)","targetColor":"rgb(255,131,255)"},"color":"rgb(255,131,255)","size":26.0},{"source":"CPS","target":"ALV","id":"30157","attributes":{"sourceColor":"rgb(255,131,255)","targetColor":"rgb(255,131,255)"},"color":"rgb(255,131,255)","size":12.0},{"source":"WBC","target":"TEN","id":"30728","attributes":{"sourceColor":"rgb(255,131,255)","targetColor":"rgb(255,131,255)"},"color":"rgb(255,131,255)","size":8.0},{"source":"THO","target":"SPAR","id":"30651","attributes":{"sourceColor":"rgb(255,131,255)","targetColor":"rgb(255,131,255)"},"color":"rgb(255,131,255)","size":3.0},{"source":"GT","target":"GNTX","id":"30397","attributes":{"sourceColor":"rgb(255,131,255)","targetColor":"rgb(255,131,255)"},"color":"rgb(255,131,255)","size":2.0},{"source":"PCAR","target":"HY","id":"30459","attributes":{"sourceColor":"rgb(255,131,255)","targetColor":"rgb(255,131,255)"},"color":"rgb(255,131,255)","size":30.0},{"source":"WBC","target":"VC","id":"30813","attributes":{"sourceColor":"rgb(255,131,255)","targetColor":"rgb(255,131,255)"},"color":"rgb(255,131,255)","size":14.0},{"source":"KNDI","target":"ALV","id":"30140","attributes":{"sourceColor":"rgb(255,131,255)","targetColor":"rgb(255,131,255)"},"color":"rgb(255,131,255)","size":2.0},{"source":"GM","target":"F","id":"30321","attributes":{"sourceColor":"rgb(255,131,255)","targetColor":"rgb(255,131,255)"},"color":"rgb(255,131,255)","size":37098.0},{"source":"WNC","target":"WBC","id":"30835","attributes":{"sourceColor":"rgb(255,131,255)","targetColor":"rgb(255,131,255)"},"color":"rgb(255,131,255)","size":17.0},{"source":"WGO","target":"LEA","id":"30502","attributes":{"sourceColor":"rgb(255,131,255)","targetColor":"rgb(255,131,255)"},"color":"rgb(255,131,255)","size":4.0},{"source":"LEA","target":"FDML","id":"30344","attributes":{"sourceColor":"rgb(255,131,255)","targetColor":"rgb(255,131,255)"},"color":"rgb(255,131,255)","size":28.0},{"source":"LEA","target":"GNTX","id":"30402","attributes":{"sourceColor":"rgb(255,131,255)","targetColor":"rgb(255,131,255)"},"color":"rgb(255,131,255)","size":178.0},{"source":"HY","target":"FSS","id":"30355","attributes":{"sourceColor":"rgb(255,131,255)","targetColor":"rgb(255,131,255)"},"color":"rgb(255,131,255)","size":50.0},{"source":"TEN","target":"GT","id":"30432","attributes":{"sourceColor":"rgb(255,131,255)","targetColor":"rgb(255,131,255)"},"color":"rgb(255,131,255)","size":43.0},{"source":"THO","target":"BWA","id":"30200","attributes":{"sourceColor":"rgb(255,131,255)","targetColor":"rgb(255,131,255)"},"color":"rgb(255,131,255)","size":4.0},{"source":"TEN","target":"FDML","id":"30334","attributes":{"sourceColor":"rgb(255,131,255)","targetColor":"rgb(255,131,255)"},"color":"rgb(255,131,255)","size":46.0},{"source":"WNC","target":"LEA","id":"30488","attributes":{"sourceColor":"rgb(255,131,255)","targetColor":"rgb(255,131,255)"},"color":"rgb(255,131,255)","size":4.0},{"source":"SPAR","target":"PII","id":"30585","attributes":{"sourceColor":"rgb(255,131,255)","targetColor":"rgb(255,131,255)"},"color":"rgb(255,131,255)","size":4.0},{"source":"HAR","target":"FDML","id":"30342","attributes":{"sourceColor":"rgb(255,131,255)","targetColor":"rgb(255,131,255)"},"color":"rgb(255,131,255)","size":34.0},{"source":"WNC","target":"FSS","id":"30349","attributes":{"sourceColor":"rgb(255,131,255)","targetColor":"rgb(255,131,255)"},"color":"rgb(255,131,255)","size":4.0},{"source":"WGO","target":"SPAR","id":"30636","attributes":{"sourceColor":"rgb(255,131,255)","targetColor":"rgb(255,131,255)"},"color":"rgb(255,131,255)","size":7.0},{"source":"WNC","target":"HY","id":"30449","attributes":{"sourceColor":"rgb(255,131,255)","targetColor":"rgb(255,131,255)"},"color":"rgb(255,131,255)","size":36.0},{"source":"WNC","target":"PCAR","id":"30570","attributes":{"sourceColor":"rgb(255,131,255)","targetColor":"rgb(255,131,255)"},"color":"rgb(255,131,255)","size":30.0},{"source":"SUP","target":"SRI","id":"30671","attributes":{"sourceColor":"rgb(255,131,255)","targetColor":"rgb(255,131,255)"},"color":"rgb(255,131,255)","size":18.0},{"source":"TEN","target":"MTOR","id":"30535","attributes":{"sourceColor":"rgb(255,131,255)","targetColor":"rgb(255,131,255)"},"color":"rgb(255,131,255)","size":2.0},{"source":"WNC","target":"AXL","id":"30176","attributes":{"sourceColor":"rgb(255,131,255)","targetColor":"rgb(255,131,255)"},"color":"rgb(255,131,255)","size":1.0},{"source":"SPAR","target":"SORL","id":"30627","attributes":{"sourceColor":"rgb(255,131,255)","targetColor":"rgb(255,131,255)"},"color":"rgb(255,131,255)","size":10.0},{"source":"WNC","target":"TEX","id":"30761","attributes":{"sourceColor":"rgb(255,131,255)","targetColor":"rgb(255,131,255)"},"color":"rgb(255,131,255)","size":6.0},{"source":"LCII","target":"F","id":"30303","attributes":{"sourceColor":"rgb(255,131,255)","targetColor":"rgb(255,131,255)"},"color":"rgb(255,131,255)","size":2.0},{"source":"SORL","target":"CAAS","id":"30227","attributes":{"sourceColor":"rgb(255,131,255)","targetColor":"rgb(255,131,255)"},"color":"rgb(255,131,255)","size":215.0},{"source":"PII","target":"LEA","id":"30498","attributes":{"sourceColor":"rgb(255,131,255)","targetColor":"rgb(255,131,255)"},"color":"rgb(255,131,255)","size":6.0},{"source":"AXL","target":"ALV","id":"30156","attributes":{"sourceColor":"rgb(255,131,255)","targetColor":"rgb(255,131,255)"},"color":"rgb(255,131,255)","size":52.0},{"source":"SPAR","target":"MTOR","id":"30542","attributes":{"sourceColor":"rgb(255,131,255)","targetColor":"rgb(255,131,255)"},"color":"rgb(255,131,255)","size":16.0},{"source":"WBC","target":"CTB","id":"30250","attributes":{"sourceColor":"rgb(255,131,255)","targetColor":"rgb(255,131,255)"},"color":"rgb(255,131,255)","size":14.0},{"source":"TEX","target":"TEN","id":"30747","attributes":{"sourceColor":"rgb(255,131,255)","targetColor":"rgb(255,131,255)"},"color":"rgb(255,131,255)","size":14.0},{"source":"MTOR","target":"HY","id":"30453","attributes":{"sourceColor":"rgb(255,131,255)","targetColor":"rgb(255,131,255)"},"color":"rgb(255,131,255)","size":16.0},{"source":"THO","target":"KNDI","id":"30466","attributes":{"sourceColor":"rgb(255,131,255)","targetColor":"rgb(255,131,255)"},"color":"rgb(255,131,255)","size":2.0},{"source":"VC","target":"STS","id":"30690","attributes":{"sourceColor":"rgb(255,131,255)","targetColor":"rgb(255,131,255)"},"color":"rgb(255,131,255)","size":2.0},{"source":"SUP","target":"CPS","id":"30239","attributes":{"sourceColor":"rgb(255,131,255)","targetColor":"rgb(255,131,255)"},"color":"rgb(255,131,255)","size":12.0},{"source":"TEN","target":"PII","id":"30592","attributes":{"sourceColor":"rgb(255,131,255)","targetColor":"rgb(255,131,255)"},"color":"rgb(255,131,255)","size":2.0},{"source":"TEN","target":"STRT","id":"30685","attributes":{"sourceColor":"rgb(255,131,255)","targetColor":"rgb(255,131,255)"},"color":"rgb(255,131,255)","size":2.0},{"source":"WGO","target":"GM","id":"30384","attributes":{"sourceColor":"rgb(255,131,255)","targetColor":"rgb(255,131,255)"},"color":"rgb(255,131,255)","size":30.0},{"source":"REVG","target":"WGO","id":"30852","attributes":{"sourceColor":"rgb(255,131,255)","targetColor":"rgb(255,131,255)"},"color":"rgb(255,131,255)","size":45.0},{"source":"FDML","target":"DAN","id":"30276","attributes":{"sourceColor":"rgb(255,131,255)","targetColor":"rgb(255,131,255)"},"color":"rgb(255,131,255)","size":34.0},{"source":"PII","target":"BGG","id":"30184","attributes":{"sourceColor":"rgb(255,131,255)","targetColor":"rgb(255,131,255)"},"color":"rgb(255,131,255)","size":2.0},{"source":"PII","target":"GT","id":"30416","attributes":{"sourceColor":"rgb(255,131,255)","targetColor":"rgb(255,131,255)"},"color":"rgb(255,131,255)","size":6.0},{"source":"THO","target":"SORL","id":"30623","attributes":{"sourceColor":"rgb(255,131,255)","targetColor":"rgb(255,131,255)"},"color":"rgb(255,131,255)","size":8.0},{"source":"PII","target":"CTB","id":"30266","attributes":{"sourceColor":"rgb(255,131,255)","targetColor":"rgb(255,131,255)"},"color":"rgb(255,131,255)","size":2.0},{"source":"MNTX","target":"KNDI","id":"30463","attributes":{"sourceColor":"rgb(255,131,255)","targetColor":"rgb(255,131,255)"},"color":"rgb(255,131,255)","size":2.0},{"source":"HY","target":"F","id":"30316","attributes":{"sourceColor":"rgb(255,131,255)","targetColor":"rgb(255,131,255)"},"color":"rgb(255,131,255)","size":6.0},{"source":"SUP","target":"STRT","id":"30674","attributes":{"sourceColor":"rgb(255,131,255)","targetColor":"rgb(255,131,255)"},"color":"rgb(255,131,255)","size":2.0},{"source":"LCII","target":"STRT","id":"30680","attributes":{"sourceColor":"rgb(255,131,255)","targetColor":"rgb(255,131,255)"},"color":"rgb(255,131,255)","size":1.0},{"source":"GM","target":"BWA","id":"30203","attributes":{"sourceColor":"rgb(255,131,255)","targetColor":"rgb(255,131,255)"},"color":"rgb(255,131,255)","size":109.0},{"source":"WNC","target":"SUP","id":"30710","attributes":{"sourceColor":"rgb(255,131,255)","targetColor":"rgb(255,131,255)"},"color":"rgb(255,131,255)","size":2.0},{"source":"WBC","target":"SPAR","id":"30654","attributes":{"sourceColor":"rgb(255,131,255)","targetColor":"rgb(255,131,255)"},"color":"rgb(255,131,255)","size":3.0},{"source":"STS","target":"BWA","id":"30198","attributes":{"sourceColor":"rgb(255,131,255)","targetColor":"rgb(255,131,255)"},"color":"rgb(255,131,255)","size":2.0},{"source":"SUP","target":"CTB","id":"30260","attributes":{"sourceColor":"rgb(255,131,255)","targetColor":"rgb(255,131,255)"},"color":"rgb(255,131,255)","size":2.0},{"source":"WGO","target":"DAN","id":"30280","attributes":{"sourceColor":"rgb(255,131,255)","targetColor":"rgb(255,131,255)"},"color":"rgb(255,131,255)","size":16.0},{"source":"GM","target":"CAAS","id":"30224","attributes":{"sourceColor":"rgb(255,131,255)","targetColor":"rgb(255,131,255)"},"color":"rgb(255,131,255)","size":3.0},{"source":"PCAR","target":"FSS","id":"30360","attributes":{"sourceColor":"rgb(255,131,255)","targetColor":"rgb(255,131,255)"},"color":"rgb(255,131,255)","size":30.0},{"source":"STRT","target":"MTOR","id":"30536","attributes":{"sourceColor":"rgb(255,131,255)","targetColor":"rgb(255,131,255)"},"color":"rgb(255,131,255)","size":12.0},{"source":"CPS","target":"AXL","id":"30178","attributes":{"sourceColor":"rgb(255,131,255)","targetColor":"rgb(255,131,255)"},"color":"rgb(255,131,255)","size":22.0},{"source":"LCII","target":"PII","id":"30590","attributes":{"sourceColor":"rgb(255,131,255)","targetColor":"rgb(255,131,255)"},"color":"rgb(255,131,255)","size":63.0},{"source":"DAN","target":"CPS","id":"30243","attributes":{"sourceColor":"rgb(255,131,255)","targetColor":"rgb(255,131,255)"},"color":"rgb(255,131,255)","size":26.0},{"source":"STS","target":"MLR","id":"30517","attributes":{"sourceColor":"rgb(255,131,255)","targetColor":"rgb(255,131,255)"},"color":"rgb(255,131,255)","size":2.0},{"source":"SMP","target":"GNTX","id":"30403","attributes":{"sourceColor":"rgb(255,131,255)","targetColor":"rgb(255,131,255)"},"color":"rgb(255,131,255)","size":2.0},{"source":"SRI","target":"DAN","id":"30270","attributes":{"sourceColor":"rgb(255,131,255)","targetColor":"rgb(255,131,255)"},"color":"rgb(255,131,255)","size":42.0},{"source":"TEX","target":"GM","id":"30389","attributes":{"sourceColor":"rgb(255,131,255)","targetColor":"rgb(255,131,255)"},"color":"rgb(255,131,255)","size":16.0},{"source":"WNC","target":"F","id":"30302","attributes":{"sourceColor":"rgb(255,131,255)","targetColor":"rgb(255,131,255)"},"color":"rgb(255,131,255)","size":3.0},{"source":"CAAS","target":"ALV","id":"30141","attributes":{"sourceColor":"rgb(255,131,255)","targetColor":"rgb(255,131,255)"},"color":"rgb(255,131,255)","size":2.0},{"source":"GNTX","target":"ALV","id":"30158","attributes":{"sourceColor":"rgb(255,131,255)","targetColor":"rgb(255,131,255)"},"color":"rgb(255,131,255)","size":100.0},{"source":"VC","target":"SPAR","id":"30655","attributes":{"sourceColor":"rgb(255,131,255)","targetColor":"rgb(255,131,255)"},"color":"rgb(255,131,255)","size":8.0},{"source":"STRT","target":"BGG","id":"30187","attributes":{"sourceColor":"rgb(255,131,255)","targetColor":"rgb(255,131,255)"},"color":"rgb(255,131,255)","size":14.0},{"source":"PII","target":"GNTX","id":"30405","attributes":{"sourceColor":"rgb(255,131,255)","targetColor":"rgb(255,131,255)"},"color":"rgb(255,131,255)","size":16.0},{"source":"LCII","target":"DAN","id":"30296","attributes":{"sourceColor":"rgb(255,131,255)","targetColor":"rgb(255,131,255)"},"color":"rgb(255,131,255)","size":1.0},{"source":"WGO","target":"VC","id":"30802","attributes":{"sourceColor":"rgb(255,131,255)","targetColor":"rgb(255,131,255)"},"color":"rgb(255,131,255)","size":4.0},{"source":"TEX","target":"HY","id":"30446","attributes":{"sourceColor":"rgb(255,131,255)","targetColor":"rgb(255,131,255)"},"color":"rgb(255,131,255)","size":20.0},{"source":"VC","target":"THO","id":"30786","attributes":{"sourceColor":"rgb(255,131,255)","targetColor":"rgb(255,131,255)"},"color":"rgb(255,131,255)","size":2.0},{"source":"PCAR","target":"BWA","id":"30193","attributes":{"sourceColor":"rgb(255,131,255)","targetColor":"rgb(255,131,255)"},"color":"rgb(255,131,255)","size":2.0},{"source":"SRI","target":"GM","id":"30380","attributes":{"sourceColor":"rgb(255,131,255)","targetColor":"rgb(255,131,255)"},"color":"rgb(255,131,255)","size":4.0},{"source":"THO","target":"HY","id":"30450","attributes":{"sourceColor":"rgb(255,131,255)","targetColor":"rgb(255,131,255)"},"color":"rgb(255,131,255)","size":2.0},{"source":"SPAR","target":"LDL","id":"30477","attributes":{"sourceColor":"rgb(255,131,255)","targetColor":"rgb(255,131,255)"},"color":"rgb(255,131,255)","size":10.0},{"source":"LEA","target":"AXL","id":"30171","attributes":{"sourceColor":"rgb(255,131,255)","targetColor":"rgb(255,131,255)"},"color":"rgb(255,131,255)","size":62.0},{"source":"SUP","target":"ALV","id":"30155","attributes":{"sourceColor":"rgb(255,131,255)","targetColor":"rgb(255,131,255)"},"color":"rgb(255,131,255)","size":42.0},{"source":"WBC","target":"GT","id":"30423","attributes":{"sourceColor":"rgb(255,131,255)","targetColor":"rgb(255,131,255)"},"color":"rgb(255,131,255)","size":2.0},{"source":"WNC","target":"MTOR","id":"30534","attributes":{"sourceColor":"rgb(255,131,255)","targetColor":"rgb(255,131,255)"},"color":"rgb(255,131,255)","size":34.0},{"source":"TEX","target":"FDML","id":"30331","attributes":{"sourceColor":"rgb(255,131,255)","targetColor":"rgb(255,131,255)"},"color":"rgb(255,131,255)","size":14.0}]}