{"nodes":[{"label":"KODK","x":149.44342041015625,"y":-259.9913024902344,"id":"KODK","clusterName":"Hshld","attributes":{"Industry":"Hshld","Centrality Measures":"","Closeness Centrality":"0.551","Harmonic Closeness Centrality":"0.61","Betweenness Centrality":"23.3","Eigenvector Centrality":"0.307","Other Measures":"","Degree":"9.0","Weighted Degree":"1114.0","Eccentricity":"3.0"},"color":"rgb(149,220,255)","size":40.08100891113281},{"label":"WEBR","x":-644.2852783203125,"y":225.56900024414062,"id":"WEBR","clusterName":"Hshld","attributes":{"Industry":"Hshld","Centrality Measures":"","Closeness Centrality":"0.521","Harmonic Closeness Centrality":"0.583","Betweenness Centrality":"9.341","Eigenvector Centrality":"0.334","Other Measures":"","Degree":"8.0","Weighted Degree":"39.0","Eccentricity":"3.0"},"color":"rgb(149,220,255)","size":11.053105354309082},{"label":"EL","x":199.3142547607422,"y":149.9971466064453,"id":"EL","clusterName":"Hshld","attributes":{"Industry":"Hshld","Centrality Measures":"","Closeness Centrality":"0.633","Harmonic Closeness Centrality":"0.719","Betweenness Centrality":"16.8","Eigenvector Centrality":"0.901","Other Measures":"","Degree":"17.0","Weighted Degree":"1480.0","Eccentricity":"3.0"},"color":"rgb(149,220,255)","size":49.96399688720703},{"label":"APOG","x":433.4315185546875,"y":26.92925453186035,"id":"APOG","clusterName":"Hshld","attributes":{"Industry":"Hshld","Centrality Measures":"","Closeness Centrality":"0.559","Harmonic Closeness Centrality":"0.632","Betweenness Centrality":"3.772","Eigenvector Centrality":"0.65","Other Measures":"","Degree":"11.0","Weighted Degree":"372.0","Eccentricity":"3.0"},"color":"rgb(149,220,255)","size":20.04500389099121},{"label":"SPB","x":461.130859375,"y":224.9252166748047,"id":"SPB","clusterName":"Hshld","attributes":{"Industry":"Hshld","Centrality Measures":"","Closeness Centrality":"0.585","Harmonic Closeness Centrality":"0.671","Betweenness Centrality":"16.639","Eigenvector Centrality":"0.697","Other Measures":"","Degree":"14.0","Weighted Degree":"74.0","Eccentricity":"3.0"},"color":"rgb(149,220,255)","size":11.998199462890625},{"label":"ODC","x":-697.2433471679688,"y":0.8491958379745483,"id":"ODC","clusterName":"Hshld","attributes":{"Industry":"Hshld","Centrality Measures":"","Closeness Centrality":"0.422","Harmonic Closeness Centrality":"0.456","Betweenness Centrality":"0.476","Eigenvector Centrality":"0.078","Other Measures":"","Degree":"2.0","Weighted Degree":"13.0","Eccentricity":"3.0"},"color":"rgb(149,220,255)","size":10.351035118103027},{"label":"MOV","x":-72.6332015991211,"y":520.2360229492188,"id":"MOV","clusterName":"Hshld","attributes":{"Industry":"Hshld","Centrality Measures":"","Closeness Centrality":"0.514","Harmonic Closeness Centrality":"0.57","Betweenness Centrality":"5.67","Eigenvector Centrality":"0.341","Other Measures":"","Degree":"7.0","Weighted Degree":"71.0","Eccentricity":"3.0"},"color":"rgb(149,220,255)","size":11.917191505432129},{"label":"APD","x":244.20423889160156,"y":-57.963314056396484,"id":"APD","clusterName":"Hshld","attributes":{"Industry":"Hshld","Centrality Measures":"","Closeness Centrality":"0.613","Harmonic Closeness Centrality":"0.693","Betweenness Centrality":"6.623","Eigenvector Centrality":"0.877","Other Measures":"","Degree":"15.0","Weighted Degree":"1306.0","Eccentricity":"3.0"},"color":"rgb(149,220,255)","size":45.265525817871094},{"label":"TPX","x":-169.43812561035156,"y":-450.2083740234375,"id":"TPX","clusterName":"Hshld","attributes":{"Industry":"Hshld","Centrality Measures":"","Closeness Centrality":"0.567","Harmonic Closeness Centrality":"0.645","Betweenness Centrality":"12.37","Eigenvector Centrality":"0.569","Other Measures":"","Degree":"12.0","Weighted Degree":"92.0","Eccentricity":"3.0"},"color":"rgb(149,220,255)","size":12.484248161315918},{"label":"CHD","x":-80.22098541259766,"y":-254.5113067626953,"id":"CHD","clusterName":"Hshld","attributes":{"Industry":"Hshld","Centrality Measures":"","Closeness Centrality":"0.603","Harmonic Closeness Centrality":"0.697","Betweenness Centrality":"9.988","Eigenvector Centrality":"0.869","Other Measures":"","Degree":"16.0","Weighted Degree":"1260.0","Eccentricity":"3.0"},"color":"rgb(149,220,255)","size":44.02340316772461},{"label":"KVUE","x":-194.2424774169922,"y":691.0742797851562,"id":"KVUE","clusterName":"Hshld","attributes":{"Industry":"Hshld","Centrality Measures":"","Closeness Centrality":"0.4","Harmonic Closeness Centrality":"0.43","Betweenness Centrality":"0.0","Eigenvector Centrality":"0.068","Other Measures":"","Degree":"1.0","Weighted Degree":"1.0","Eccentricity":"4.0"},"color":"rgb(149,220,255)","size":10.027002334594727},{"label":"FGH","x":10.417427062988281,"y":-700.3588256835938,"id":"FGH","clusterName":"Hshld","attributes":{"Industry":"Hshld","Centrality Measures":"","Closeness Centrality":"0.384","Harmonic Closeness Centrality":"0.421","Betweenness Centrality":"0.511","Eigenvector Centrality":"0.047","Other Measures":"","Degree":"2.0","Weighted Degree":"10.0","Eccentricity":"4.0"},"color":"rgb(149,220,255)","size":10.270027160644531},{"label":"HOFT","x":-552.5133056640625,"y":-404.6824645996094,"id":"HOFT","clusterName":"Hshld","attributes":{"Industry":"Hshld","Centrality Measures":"","Closeness Centrality":"0.521","Harmonic Closeness Centrality":"0.583","Betweenness Centrality":"4.298","Eigenvector Centrality":"0.389","Other Measures":"","Degree":"8.0","Weighted Degree":"37.0","Eccentricity":"3.0"},"color":"rgb(149,220,255)","size":10.999099731445312},{"label":"AOS","x":-199.25735473632812,"y":350.33740234375,"id":"AOS","clusterName":"Hshld","attributes":{"Industry":"Hshld","Centrality Measures":"","Closeness Centrality":"0.594","Harmonic Closeness Centrality":"0.667","Betweenness Centrality":"2.986","Eigenvector Centrality":"0.787","Other Measures":"","Degree":"13.0","Weighted Degree":"814.0","Eccentricity":"3.0"},"color":"rgb(149,220,255)","size":31.98019790649414},{"label":"COOK","x":662.3546752929688,"y":12.615347862243652,"id":"COOK","clusterName":"Hshld","attributes":{"Industry":"Hshld","Centrality Measures":"","Closeness Centrality":"0.535","Harmonic Closeness Centrality":"0.601","Betweenness Centrality":"24.392","Eigenvector Centrality":"0.313","Other Measures":"","Degree":"9.0","Weighted Degree":"53.0","Eccentricity":"3.0"},"color":"rgb(149,220,255)","size":11.431142807006836},{"label":"EPC","x":-412.0860900878906,"y":297.189697265625,"id":"EPC","clusterName":"Hshld","attributes":{"Industry":"Hshld","Centrality Measures":"","Closeness Centrality":"0.507","Harmonic Closeness Centrality":"0.566","Betweenness Centrality":"0.75","Eigenvector Centrality":"0.427","Other Measures":"","Degree":"7.0","Weighted Degree":"77.0","Eccentricity":"3.0"},"color":"rgb(149,220,255)","size":12.079208374023438},{"label":"CL","x":-54.885765075683594,"y":136.8734893798828,"id":"CL","clusterName":"Hshld","attributes":{"Industry":"Hshld","Centrality Measures":"","Closeness Centrality":"0.679","Harmonic Closeness Centrality":"0.763","Betweenness Centrality":"39.406","Eigenvector Centrality":"1.0","Other Measures":"","Degree":"20.0","Weighted Degree":"2220.0","Eccentricity":"2.0"},"color":"rgb(149,220,255)","size":69.94599914550781},{"label":"PG","x":20.23336410522461,"y":-56.19309997558594,"id":"PG","clusterName":"Hshld","attributes":{"Industry":"Hshld","Centrality Measures":"","Closeness Centrality":"0.655","Harmonic Closeness Centrality":"0.754","Betweenness Centrality":"80.97","Eigenvector Centrality":"0.939","Other Measures":"","Degree":"20.0","Weighted Degree":"2222.0","Eccentricity":"3.0"},"color":"rgb(149,220,255)","size":70.0},{"label":"COTY","x":-441.8968505859375,"y":-132.34603881835938,"id":"COTY","clusterName":"Hshld","attributes":{"Industry":"Hshld","Centrality Measures":"","Closeness Centrality":"0.633","Harmonic Closeness Centrality":"0.711","Betweenness Centrality":"27.126","Eigenvector Centrality":"0.803","Other Measures":"","Degree":"16.0","Weighted Degree":"276.0","Eccentricity":"2.0"},"color":"rgb(149,220,255)","size":17.45274543762207},{"label":"BRDS","x":306.726318359375,"y":-388.4056701660156,"id":"BRDS","clusterName":"Hshld","attributes":{"Industry":"Hshld","Centrality Measures":"","Closeness Centrality":"0.521","Harmonic Closeness Centrality":"0.592","Betweenness Centrality":"29.341","Eigenvector Centrality":"0.333","Other Measures":"","Degree":"9.0","Weighted Degree":"84.0","Eccentricity":"3.0"},"color":"rgb(149,220,255)","size":12.268226623535156},{"label":"SNBR","x":151.4243621826172,"y":514.041748046875,"id":"SNBR","clusterName":"Hshld","attributes":{"Industry":"Hshld","Centrality Measures":"","Closeness Centrality":"0.514","Harmonic Closeness Centrality":"0.579","Betweenness Centrality":"5.013","Eigenvector Centrality":"0.372","Other Measures":"","Degree":"8.0","Weighted Degree":"65.0","Eccentricity":"3.0"},"color":"rgb(149,220,255)","size":11.755175590515137},{"label":"HOG","x":52.59296798706055,"y":-470.42303466796875,"id":"HOG","clusterName":"Hshld","attributes":{"Industry":"Hshld","Centrality Measures":"","Closeness Centrality":"0.655","Harmonic Closeness Centrality":"0.746","Betweenness Centrality":"62.665","Eigenvector Centrality":"0.884","Other Measures":"","Degree":"19.0","Weighted Degree":"216.0","Eccentricity":"3.0"},"color":"rgb(149,220,255)","size":15.8325834274292},{"label":"CRVO","x":-555.7083129882812,"y":455.9266662597656,"id":"CRVO","clusterName":"Hshld","attributes":{"Industry":"Hshld","Centrality Measures":"","Closeness Centrality":"0.0","Harmonic Closeness Centrality":"0.0","Betweenness Centrality":"0.0","Eigenvector Centrality":"0.0","Other Measures":"","Degree":"0.0","Weighted Degree":"0.0","Eccentricity":"0.0"},"color":"rgb(149,220,255)","size":10.0},{"label":"ECL","x":43.833805084228516,"y":312.0577087402344,"id":"ECL","clusterName":"Hshld","attributes":{"Industry":"Hshld","Centrality Measures":"","Closeness Centrality":"0.623","Harmonic Closeness Centrality":"0.697","Betweenness Centrality":"28.651","Eigenvector Centrality":"0.8","Other Measures":"","Degree":"15.0","Weighted Degree":"844.0","Eccentricity":"2.0"},"color":"rgb(149,220,255)","size":32.790279388427734},{"label":"CLX","x":-216.83731079101562,"y":-85.45431518554688,"id":"CLX","clusterName":"Hshld","attributes":{"Industry":"Hshld","Centrality Measures":"","Closeness Centrality":"0.603","Harmonic Closeness Centrality":"0.697","Betweenness Centrality":"41.184","Eigenvector Centrality":"0.78","Other Measures":"","Degree":"16.0","Weighted Degree":"1966.0","Eccentricity":"3.0"},"color":"rgb(149,220,255)","size":63.08730697631836},{"label":"NUS","x":-352.29608154296875,"y":538.3742065429688,"id":"NUS","clusterName":"Hshld","attributes":{"Industry":"Hshld","Centrality Measures":"","Closeness Centrality":"0.528","Harmonic Closeness Centrality":"0.596","Betweenness Centrality":"8.422","Eigenvector Centrality":"0.438","Other Measures":"","Degree":"9.0","Weighted Degree":"55.0","Eccentricity":"3.0"},"color":"rgb(149,220,255)","size":11.485148429870605},{"label":"WULF","x":-258.66925048828125,"y":120.21300506591797,"id":"WULF","clusterName":"Hshld","attributes":{"Industry":"Hshld","Centrality Measures":"","Closeness Centrality":"0.551","Harmonic Closeness Centrality":"0.618","Betweenness Centrality":"14.045","Eigenvector Centrality":"0.414","Other Measures":"","Degree":"10.0","Weighted Degree":"1150.0","Eccentricity":"3.0"},"color":"rgb(149,220,255)","size":41.05310821533203},{"label":"FORD","x":350.70458984375,"y":600.8828735351562,"id":"FORD","clusterName":"Hshld","attributes":{"Industry":"Hshld","Centrality Measures":"","Closeness Centrality":"0.5","Harmonic Closeness Centrality":"0.561","Betweenness Centrality":"8.829","Eigenvector Centrality":"0.277","Other Measures":"","Degree":"7.0","Weighted Degree":"16.0","Eccentricity":"3.0"},"color":"rgb(149,220,255)","size":10.432043075561523},{"label":"CPSH","x":676.8549194335938,"y":239.62661743164062,"id":"CPSH","clusterName":"Hshld","attributes":{"Industry":"Hshld","Centrality Measures":"","Closeness Centrality":"0.0","Harmonic Closeness Centrality":"0.0","Betweenness Centrality":"0.0","Eigenvector Centrality":"0.0","Other Measures":"","Degree":"0.0","Weighted Degree":"0.0","Eccentricity":"0.0"},"color":"rgb(149,220,255)","size":10.0},{"label":"FLXS","x":-402.1845397949219,"y":-560.3978271484375,"id":"FLXS","clusterName":"Hshld","attributes":{"Industry":"Hshld","Centrality Measures":"","Closeness Centrality":"0.452","Harmonic Closeness Centrality":"0.5","Betweenness Centrality":"3.625","Eigenvector Centrality":"0.154","Other Measures":"","Degree":"4.0","Weighted Degree":"17.0","Eccentricity":"3.0"},"color":"rgb(149,220,255)","size":10.459046363830566},{"label":"LEG","x":-337.0860290527344,"y":-311.098876953125,"id":"LEG","clusterName":"Hshld","attributes":{"Industry":"Hshld","Centrality Measures":"","Closeness Centrality":"0.594","Harmonic Closeness Centrality":"0.675","Betweenness Centrality":"16.182","Eigenvector Centrality":"0.738","Other Measures":"","Degree":"14.0","Weighted Degree":"324.0","Eccentricity":"3.0"},"color":"rgb(149,220,255)","size":18.74887466430664},{"label":"ELF","x":87.05247497558594,"y":714.1068725585938,"id":"ELF","clusterName":"Hshld","attributes":{"Industry":"Hshld","Centrality Measures":"","Closeness Centrality":"0.0","Harmonic Closeness Centrality":"0.0","Betweenness Centrality":"0.0","Eigenvector Centrality":"0.0","Other Measures":"","Degree":"0.0","Weighted Degree":"0.0","Eccentricity":"0.0"},"color":"rgb(149,220,255)","size":10.0},{"label":"MITQ","x":558.0841674804688,"y":-389.8030700683594,"id":"MITQ","clusterName":"Hshld","attributes":{"Industry":"Hshld","Centrality Measures":"","Closeness Centrality":"0.447","Harmonic Closeness Centrality":"0.496","Betweenness Centrality":"1.306","Eigenvector Centrality":"0.138","Other Measures":"","Degree":"4.0","Weighted Degree":"41.0","Eccentricity":"3.0"},"color":"rgb(149,220,255)","size":11.107110977172852},{"label":"HBB","x":424.7384338378906,"y":-571.1109619140625,"id":"HBB","clusterName":"Hshld","attributes":{"Industry":"Hshld","Centrality Measures":"","Closeness Centrality":"0.422","Harmonic Closeness Centrality":"0.458","Betweenness Centrality":"0.0","Eigenvector Centrality":"0.088","Other Measures":"","Degree":"2.0","Weighted Degree":"4.0","Eccentricity":"4.0"},"color":"rgb(149,220,255)","size":10.108011245727539},{"label":"DFFN","x":677.4902954101562,"y":-196.0026092529297,"id":"DFFN","clusterName":"Hshld","attributes":{"Industry":"Hshld","Centrality Measures":"","Closeness Centrality":"0.447","Harmonic Closeness Centrality":"0.489","Betweenness Centrality":"3.411","Eigenvector Centrality":"0.104","Other Measures":"","Degree":"3.0","Weighted Degree":"8.0","Eccentricity":"4.0"},"color":"rgb(149,220,255)","size":10.216021537780762},{"label":"NC","x":525.2716674804688,"y":443.5268249511719,"id":"NC","clusterName":"Hshld","attributes":{"Industry":"Hshld","Centrality Measures":"","Closeness Centrality":"0.543","Harmonic Closeness Centrality":"0.596","Betweenness Centrality":"32.532","Eigenvector Centrality":"0.284","Other Measures":"","Degree":"8.0","Weighted Degree":"36.0","Eccentricity":"3.0"},"color":"rgb(149,220,255)","size":10.972097396850586},{"label":"CTHR","x":-655.0803833007812,"y":-214.68704223632812,"id":"CTHR","clusterName":"Hshld","attributes":{"Industry":"Hshld","Centrality Measures":"","Closeness Centrality":"0.458","Harmonic Closeness Centrality":"0.496","Betweenness Centrality":"0.213","Eigenvector Centrality":"0.183","Other Measures":"","Degree":"3.0","Weighted Degree":"33.0","Eccentricity":"3.0"},"color":"rgb(149,220,255)","size":10.89108943939209},{"label":"BSET","x":-207.5439453125,"y":-667.2852783203125,"id":"BSET","clusterName":"Hshld","attributes":{"Industry":"Hshld","Centrality Measures":"","Closeness Centrality":"0.442","Harmonic Closeness Centrality":"0.474","Betweenness Centrality":"0.311","Eigenvector Centrality":"0.096","Other Measures":"","Degree":"2.0","Weighted Degree":"12.0","Eccentricity":"3.0"},"color":"rgb(149,220,255)","size":10.3240327835083},{"label":"FOSL","x":216.3601837158203,"y":-634.8642578125,"id":"FOSL","clusterName":"Hshld","attributes":{"Industry":"Hshld","Centrality Measures":"","Closeness Centrality":"0.447","Harmonic Closeness Centrality":"0.496","Betweenness Centrality":"0.978","Eigenvector Centrality":"0.132","Other Measures":"","Degree":"4.0","Weighted Degree":"44.0","Eccentricity":"3.0"},"color":"rgb(149,220,255)","size":11.188118934631348},{"label":"TPR","x":436.8343505859375,"y":-197.30422973632812,"id":"TPR","clusterName":"Hshld","attributes":{"Industry":"Hshld","Centrality Measures":"","Closeness Centrality":"0.613","Harmonic Closeness Centrality":"0.711","Betweenness Centrality":"34.97","Eigenvector Centrality":"0.852","Other Measures":"","Degree":"17.0","Weighted Degree":"183.0","Eccentricity":"3.0"},"color":"rgb(149,220,255)","size":14.94149398803711},{"label":"WHR","x":-472.7290344238281,"y":73.7724838256836,"id":"WHR","clusterName":"Hshld","attributes":{"Industry":"Hshld","Centrality Measures":"","Closeness Centrality":"0.691","Harmonic Closeness Centrality":"0.776","Betweenness Centrality":"77.032","Eigenvector Centrality":"0.979","Other Measures":"","Degree":"21.0","Weighted Degree":"199.0","Eccentricity":"2.0"},"color":"rgb(149,220,255)","size":15.373537063598633},{"label":"GLW","x":288.3388671875,"y":353.9667663574219,"id":"GLW","clusterName":"Hshld","attributes":{"Industry":"Hshld","Centrality Measures":"","Closeness Centrality":"0.585","Harmonic Closeness Centrality":"0.671","Betweenness Centrality":"5.87","Eigenvector Centrality":"0.809","Other Measures":"","Degree":"14.0","Weighted Degree":"354.0","Eccentricity":"3.0"},"color":"rgb(149,220,255)","size":19.558956146240234}],"edges":[{"source":"CLX","target":"CL","id":"44124","attributes":{"sourceColor":"rgb(149,220,255)","targetColor":"rgb(149,220,255)"},"color":"rgb(149,220,255)","size":507.0},{"source":"COTY","target":"CLX","id":"44149","attributes":{"sourceColor":"rgb(149,220,255)","targetColor":"rgb(149,220,255)"},"color":"rgb(149,220,255)","size":16.0},{"source":"WHR","target":"SNBR","id":"44350","attributes":{"sourceColor":"rgb(149,220,255)","targetColor":"rgb(149,220,255)"},"color":"rgb(149,220,255)","size":4.0},{"source":"WEBR","target":"EL","id":"44207","attributes":{"sourceColor":"rgb(149,220,255)","targetColor":"rgb(149,220,255)"},"color":"rgb(149,220,255)","size":4.0},{"source":"WULF","target":"NC","id":"44315","attributes":{"sourceColor":"rgb(149,220,255)","targetColor":"rgb(149,220,255)"},"color":"rgb(149,220,255)","size":2.0},{"source":"TPR","target":"AOS","id":"44055","attributes":{"sourceColor":"rgb(149,220,255)","targetColor":"rgb(149,220,255)"},"color":"rgb(149,220,255)","size":4.0},{"source":"WHR","target":"CL","id":"44131","attributes":{"sourceColor":"rgb(149,220,255)","targetColor":"rgb(149,220,255)"},"color":"rgb(149,220,255)","size":20.0},{"source":"ODC","target":"CLX","id":"44145","attributes":{"sourceColor":"rgb(149,220,255)","targetColor":"rgb(149,220,255)"},"color":"rgb(149,220,255)","size":11.0},{"source":"PG","target":"COTY","id":"44171","attributes":{"sourceColor":"rgb(149,220,255)","targetColor":"rgb(149,220,255)"},"color":"rgb(149,220,255)","size":61.0},{"source":"MITQ","target":"BRDS","id":"44093","attributes":{"sourceColor":"rgb(149,220,255)","targetColor":"rgb(149,220,255)"},"color":"rgb(149,220,255)","size":29.0},{"source":"CL","target":"KODK","id":"44281","attributes":{"sourceColor":"rgb(149,220,255)","targetColor":"rgb(149,220,255)"},"color":"rgb(149,220,255)","size":7.0},{"source":"SNBR","target":"CLX","id":"44143","attributes":{"sourceColor":"rgb(149,220,255)","targetColor":"rgb(149,220,255)"},"color":"rgb(149,220,255)","size":2.0},{"source":"HOG","target":"EL","id":"44206","attributes":{"sourceColor":"rgb(149,220,255)","targetColor":"rgb(149,220,255)"},"color":"rgb(149,220,255)","size":79.0},{"source":"ECL","target":"CL","id":"44132","attributes":{"sourceColor":"rgb(149,220,255)","targetColor":"rgb(149,220,255)"},"color":"rgb(149,220,255)","size":61.0},{"source":"TPR","target":"APD","id":"44071","attributes":{"sourceColor":"rgb(149,220,255)","targetColor":"rgb(149,220,255)"},"color":"rgb(149,220,255)","size":3.0},{"source":"WHR","target":"CHD","id":"44108","attributes":{"sourceColor":"rgb(149,220,255)","targetColor":"rgb(149,220,255)"},"color":"rgb(149,220,255)","size":7.0},{"source":"MOV","target":"EL","id":"44210","attributes":{"sourceColor":"rgb(149,220,255)","targetColor":"rgb(149,220,255)"},"color":"rgb(149,220,255)","size":48.0},{"source":"WEBR","target":"SPB","id":"44367","attributes":{"sourceColor":"rgb(149,220,255)","targetColor":"rgb(149,220,255)"},"color":"rgb(149,220,255)","size":4.0},{"source":"WHR","target":"FORD","id":"44232","attributes":{"sourceColor":"rgb(149,220,255)","targetColor":"rgb(149,220,255)"},"color":"rgb(149,220,255)","size":4.0},{"source":"WHR","target":"HOFT","id":"44254","attributes":{"sourceColor":"rgb(149,220,255)","targetColor":"rgb(149,220,255)"},"color":"rgb(149,220,255)","size":2.0},{"source":"HOG","target":"CL","id":"44134","attributes":{"sourceColor":"rgb(149,220,255)","targetColor":"rgb(149,220,255)"},"color":"rgb(149,220,255)","size":2.0},{"source":"LEG","target":"GLW","id":"44237","attributes":{"sourceColor":"rgb(149,220,255)","targetColor":"rgb(149,220,255)"},"color":"rgb(149,220,255)","size":30.0},{"source":"SPB","target":"NUS","id":"44326","attributes":{"sourceColor":"rgb(149,220,255)","targetColor":"rgb(149,220,255)"},"color":"rgb(149,220,255)","size":2.0},{"source":"TPR","target":"EL","id":"44205","attributes":{"sourceColor":"rgb(149,220,255)","targetColor":"rgb(149,220,255)"},"color":"rgb(149,220,255)","size":41.0},{"source":"BSET","target":"BRDS","id":"44094","attributes":{"sourceColor":"rgb(149,220,255)","targetColor":"rgb(149,220,255)"},"color":"rgb(149,220,255)","size":2.0},{"source":"TPR","target":"SPB","id":"44368","attributes":{"sourceColor":"rgb(149,220,255)","targetColor":"rgb(149,220,255)"},"color":"rgb(149,220,255)","size":2.0},{"source":"SPB","target":"APD","id":"44069","attributes":{"sourceColor":"rgb(149,220,255)","targetColor":"rgb(149,220,255)"},"color":"rgb(149,220,255)","size":2.0},{"source":"TPR","target":"LEG","id":"44292","attributes":{"sourceColor":"rgb(149,220,255)","targetColor":"rgb(149,220,255)"},"color":"rgb(149,220,255)","size":2.0},{"source":"CL","target":"CHD","id":"44106","attributes":{"sourceColor":"rgb(149,220,255)","targetColor":"rgb(149,220,255)"},"color":"rgb(149,220,255)","size":155.0},{"source":"TPX","target":"GLW","id":"44239","attributes":{"sourceColor":"rgb(149,220,255)","targetColor":"rgb(149,220,255)"},"color":"rgb(149,220,255)","size":4.0},{"source":"WHR","target":"APD","id":"44080","attributes":{"sourceColor":"rgb(149,220,255)","targetColor":"rgb(149,220,255)"},"color":"rgb(149,220,255)","size":6.0},{"source":"EL","target":"ECL","id":"44193","attributes":{"sourceColor":"rgb(149,220,255)","targetColor":"rgb(149,220,255)"},"color":"rgb(149,220,255)","size":21.0},{"source":"PG","target":"CHD","id":"44104","attributes":{"sourceColor":"rgb(149,220,255)","targetColor":"rgb(149,220,255)"},"color":"rgb(149,220,255)","size":136.0},{"source":"TPR","target":"CTHR","id":"44179","attributes":{"sourceColor":"rgb(149,220,255)","targetColor":"rgb(149,220,255)"},"color":"rgb(149,220,255)","size":4.0},{"source":"WHR","target":"SPB","id":"44366","attributes":{"sourceColor":"rgb(149,220,255)","targetColor":"rgb(149,220,255)"},"color":"rgb(149,220,255)","size":14.0},{"source":"SPB","target":"COTY","id":"44174","attributes":{"sourceColor":"rgb(149,220,255)","targetColor":"rgb(149,220,255)"},"color":"rgb(149,220,255)","size":2.0},{"source":"TPR","target":"NUS","id":"44321","attributes":{"sourceColor":"rgb(149,220,255)","targetColor":"rgb(149,220,255)"},"color":"rgb(149,220,255)","size":8.0},{"source":"SPB","target":"HOG","id":"44273","attributes":{"sourceColor":"rgb(149,220,255)","targetColor":"rgb(149,220,255)"},"color":"rgb(149,220,255)","size":4.0},{"source":"COTY","target":"COOK","id":"44155","attributes":{"sourceColor":"rgb(149,220,255)","targetColor":"rgb(149,220,255)"},"color":"rgb(149,220,255)","size":2.0},{"source":"ECL","target":"APD","id":"44066","attributes":{"sourceColor":"rgb(149,220,255)","targetColor":"rgb(149,220,255)"},"color":"rgb(149,220,255)","size":285.0},{"source":"EPC","target":"CL","id":"44129","attributes":{"sourceColor":"rgb(149,220,255)","targetColor":"rgb(149,220,255)"},"color":"rgb(149,220,255)","size":2.0},{"source":"TPX","target":"LEG","id":"44289","attributes":{"sourceColor":"rgb(149,220,255)","targetColor":"rgb(149,220,255)"},"color":"rgb(149,220,255)","size":28.0},{"source":"GLW","target":"EPC","id":"44218","attributes":{"sourceColor":"rgb(149,220,255)","targetColor":"rgb(149,220,255)"},"color":"rgb(149,220,255)","size":2.0},{"source":"NUS","target":"KODK","id":"44286","attributes":{"sourceColor":"rgb(149,220,255)","targetColor":"rgb(149,220,255)"},"color":"rgb(149,220,255)","size":2.0},{"source":"COTY","target":"CHD","id":"44103","attributes":{"sourceColor":"rgb(149,220,255)","targetColor":"rgb(149,220,255)"},"color":"rgb(149,220,255)","size":18.0},{"source":"PG","target":"NUS","id":"44320","attributes":{"sourceColor":"rgb(149,220,255)","targetColor":"rgb(149,220,255)"},"color":"rgb(149,220,255)","size":6.0},{"source":"CHD","target":"AOS","id":"44065","attributes":{"sourceColor":"rgb(149,220,255)","targetColor":"rgb(149,220,255)"},"color":"rgb(149,220,255)","size":140.0},{"source":"CHD","target":"APD","id":"44068","attributes":{"sourceColor":"rgb(149,220,255)","targetColor":"rgb(149,220,255)"},"color":"rgb(149,220,255)","size":156.0},{"source":"HOG","target":"COOK","id":"44160","attributes":{"sourceColor":"rgb(149,220,255)","targetColor":"rgb(149,220,255)"},"color":"rgb(149,220,255)","size":8.0},{"source":"SNBR","target":"LEG","id":"44296","attributes":{"sourceColor":"rgb(149,220,255)","targetColor":"rgb(149,220,255)"},"color":"rgb(149,220,255)","size":33.0},{"source":"HOG","target":"APOG","id":"44086","attributes":{"sourceColor":"rgb(149,220,255)","targetColor":"rgb(149,220,255)"},"color":"rgb(149,220,255)","size":2.0},{"source":"PG","target":"ECL","id":"44187","attributes":{"sourceColor":"rgb(149,220,255)","targetColor":"rgb(149,220,255)"},"color":"rgb(149,220,255)","size":16.0},{"source":"NC","target":"FGH","id":"44222","attributes":{"sourceColor":"rgb(149,220,255)","targetColor":"rgb(149,220,255)"},"color":"rgb(149,220,255)","size":6.0},{"source":"CL","target":"APD","id":"44075","attributes":{"sourceColor":"rgb(149,220,255)","targetColor":"rgb(149,220,255)"},"color":"rgb(149,220,255)","size":91.0},{"source":"EL","target":"CL","id":"44118","attributes":{"sourceColor":"rgb(149,220,255)","targetColor":"rgb(149,220,255)"},"color":"rgb(149,220,255)","size":313.0},{"source":"SPB","target":"GLW","id":"44247","attributes":{"sourceColor":"rgb(149,220,255)","targetColor":"rgb(149,220,255)"},"color":"rgb(149,220,255)","size":8.0},{"source":"ECL","target":"AOS","id":"44064","attributes":{"sourceColor":"rgb(149,220,255)","targetColor":"rgb(149,220,255)"},"color":"rgb(149,220,255)","size":58.0},{"source":"SPB","target":"AOS","id":"44063","attributes":{"sourceColor":"rgb(149,220,255)","targetColor":"rgb(149,220,255)"},"color":"rgb(149,220,255)","size":2.0},{"source":"WULF","target":"BRDS","id":"44098","attributes":{"sourceColor":"rgb(149,220,255)","targetColor":"rgb(149,220,255)"},"color":"rgb(149,220,255)","size":39.0},{"source":"GLW","target":"CL","id":"44127","attributes":{"sourceColor":"rgb(149,220,255)","targetColor":"rgb(149,220,255)"},"color":"rgb(149,220,255)","size":6.0},{"source":"FGH","target":"BRDS","id":"44099","attributes":{"sourceColor":"rgb(149,220,255)","targetColor":"rgb(149,220,255)"},"color":"rgb(149,220,255)","size":4.0},{"source":"PG","target":"EL","id":"44203","attributes":{"sourceColor":"rgb(149,220,255)","targetColor":"rgb(149,220,255)"},"color":"rgb(149,220,255)","size":388.0},{"source":"TPR","target":"GLW","id":"44243","attributes":{"sourceColor":"rgb(149,220,255)","targetColor":"rgb(149,220,255)"},"color":"rgb(149,220,255)","size":4.0},{"source":"HBB","target":"COOK","id":"44157","attributes":{"sourceColor":"rgb(149,220,255)","targetColor":"rgb(149,220,255)"},"color":"rgb(149,220,255)","size":2.0},{"source":"EL","target":"APD","id":"44077","attributes":{"sourceColor":"rgb(149,220,255)","targetColor":"rgb(149,220,255)"},"color":"rgb(149,220,255)","size":52.0},{"source":"LEG","target":"CLX","id":"44136","attributes":{"sourceColor":"rgb(149,220,255)","targetColor":"rgb(149,220,255)"},"color":"rgb(149,220,255)","size":4.0},{"source":"GLW","target":"APD","id":"44073","attributes":{"sourceColor":"rgb(149,220,255)","targetColor":"rgb(149,220,255)"},"color":"rgb(149,220,255)","size":56.0},{"source":"LEG","target":"ECL","id":"44189","attributes":{"sourceColor":"rgb(149,220,255)","targetColor":"rgb(149,220,255)"},"color":"rgb(149,220,255)","size":2.0},{"source":"PG","target":"EPC","id":"44217","attributes":{"sourceColor":"rgb(149,220,255)","targetColor":"rgb(149,220,255)"},"color":"rgb(149,220,255)","size":8.0},{"source":"PG","target":"KODK","id":"44287","attributes":{"sourceColor":"rgb(149,220,255)","targetColor":"rgb(149,220,255)"},"color":"rgb(149,220,255)","size":2.0},{"source":"SNBR","target":"CHD","id":"44111","attributes":{"sourceColor":"rgb(149,220,255)","targetColor":"rgb(149,220,255)"},"color":"rgb(149,220,255)","size":2.0},{"source":"WHR","target":"GLW","id":"44250","attributes":{"sourceColor":"rgb(149,220,255)","targetColor":"rgb(149,220,255)"},"color":"rgb(149,220,255)","size":33.0},{"source":"TPX","target":"SNBR","id":"44351","attributes":{"sourceColor":"rgb(149,220,255)","targetColor":"rgb(149,220,255)"},"color":"rgb(149,220,255)","size":14.0},{"source":"FOSL","target":"KODK","id":"44284","attributes":{"sourceColor":"rgb(149,220,255)","targetColor":"rgb(149,220,255)"},"color":"rgb(149,220,255)","size":1.0},{"source":"NUS","target":"CHD","id":"44116","attributes":{"sourceColor":"rgb(149,220,255)","targetColor":"rgb(149,220,255)"},"color":"rgb(149,220,255)","size":7.0},{"source":"HOG","target":"GLW","id":"44248","attributes":{"sourceColor":"rgb(149,220,255)","targetColor":"rgb(149,220,255)"},"color":"rgb(149,220,255)","size":9.0},{"source":"LEG","target":"APD","id":"44074","attributes":{"sourceColor":"rgb(149,220,255)","targetColor":"rgb(149,220,255)"},"color":"rgb(149,220,255)","size":6.0},{"source":"DFFN","target":"COOK","id":"44156","attributes":{"sourceColor":"rgb(149,220,255)","targetColor":"rgb(149,220,255)"},"color":"rgb(149,220,255)","size":2.0},{"source":"WULF","target":"EL","id":"44211","attributes":{"sourceColor":"rgb(149,220,255)","targetColor":"rgb(149,220,255)"},"color":"rgb(149,220,255)","size":2.0},{"source":"APOG","target":"AOS","id":"44059","attributes":{"sourceColor":"rgb(149,220,255)","targetColor":"rgb(149,220,255)"},"color":"rgb(149,220,255)","size":12.0},{"source":"HOG","target":"ECL","id":"44183","attributes":{"sourceColor":"rgb(149,220,255)","targetColor":"rgb(149,220,255)"},"color":"rgb(149,220,255)","size":10.0},{"source":"TPX","target":"EL","id":"44200","attributes":{"sourceColor":"rgb(149,220,255)","targetColor":"rgb(149,220,255)"},"color":"rgb(149,220,255)","size":1.0},{"source":"FORD","target":"CL","id":"44121","attributes":{"sourceColor":"rgb(149,220,255)","targetColor":"rgb(149,220,255)"},"color":"rgb(149,220,255)","size":2.0},{"source":"WHR","target":"BSET","id":"44100","attributes":{"sourceColor":"rgb(149,220,255)","targetColor":"rgb(149,220,255)"},"color":"rgb(149,220,255)","size":10.0},{"source":"BRDS","target":"WEBR","id":"44404","attributes":{"sourceColor":"rgb(149,220,255)","targetColor":"rgb(149,220,255)"},"color":"rgb(149,220,255)","size":1.0},{"source":"EPC","target":"COTY","id":"44170","attributes":{"sourceColor":"rgb(149,220,255)","targetColor":"rgb(149,220,255)"},"color":"rgb(149,220,255)","size":43.0},{"source":"WULF","target":"APD","id":"44072","attributes":{"sourceColor":"rgb(149,220,255)","targetColor":"rgb(149,220,255)"},"color":"rgb(149,220,255)","size":2.0},{"source":"EL","target":"COTY","id":"44173","attributes":{"sourceColor":"rgb(149,220,255)","targetColor":"rgb(149,220,255)"},"color":"rgb(149,220,255)","size":87.0},{"source":"SPB","target":"CHD","id":"44110","attributes":{"sourceColor":"rgb(149,220,255)","targetColor":"rgb(149,220,255)"},"color":"rgb(149,220,255)","size":2.0},{"source":"MOV","target":"KODK","id":"44282","attributes":{"sourceColor":"rgb(149,220,255)","targetColor":"rgb(149,220,255)"},"color":"rgb(149,220,255)","size":1.0},{"source":"EPC","target":"CHD","id":"44115","attributes":{"sourceColor":"rgb(149,220,255)","targetColor":"rgb(149,220,255)"},"color":"rgb(149,220,255)","size":2.0},{"source":"COOK","target":"CL","id":"44130","attributes":{"sourceColor":"rgb(149,220,255)","targetColor":"rgb(149,220,255)"},"color":"rgb(149,220,255)","size":2.0},{"source":"SPB","target":"NC","id":"44313","attributes":{"sourceColor":"rgb(149,220,255)","targetColor":"rgb(149,220,255)"},"color":"rgb(149,220,255)","size":12.0},{"source":"TPR","target":"PG","id":"44347","attributes":{"sourceColor":"rgb(149,220,255)","targetColor":"rgb(149,220,255)"},"color":"rgb(149,220,255)","size":26.0},{"source":"WHR","target":"PG","id":"44336","attributes":{"sourceColor":"rgb(149,220,255)","targetColor":"rgb(149,220,255)"},"color":"rgb(149,220,255)","size":17.0},{"source":"SNBR","target":"HOFT","id":"44260","attributes":{"sourceColor":"rgb(149,220,255)","targetColor":"rgb(149,220,255)"},"color":"rgb(149,220,255)","size":2.0},{"source":"FLXS","target":"WHR","id":"44414","attributes":{"sourceColor":"rgb(149,220,255)","targetColor":"rgb(149,220,255)"},"color":"rgb(149,220,255)","size":1.0},{"source":"LEG","target":"FLXS","id":"44225","attributes":{"sourceColor":"rgb(149,220,255)","targetColor":"rgb(149,220,255)"},"color":"rgb(149,220,255)","size":10.0},{"source":"HOFT","target":"FORD","id":"44229","attributes":{"sourceColor":"rgb(149,220,255)","targetColor":"rgb(149,220,255)"},"color":"rgb(149,220,255)","size":2.0},{"source":"WEBR","target":"PG","id":"44338","attributes":{"sourceColor":"rgb(149,220,255)","targetColor":"rgb(149,220,255)"},"color":"rgb(149,220,255)","size":2.0},{"source":"ECL","target":"CLX","id":"44140","attributes":{"sourceColor":"rgb(149,220,255)","targetColor":"rgb(149,220,255)"},"color":"rgb(149,220,255)","size":154.0},{"source":"CLX","target":"APOG","id":"44085","attributes":{"sourceColor":"rgb(149,220,255)","targetColor":"rgb(149,220,255)"},"color":"rgb(149,220,255)","size":2.0},{"source":"WHR","target":"LEG","id":"44293","attributes":{"sourceColor":"rgb(149,220,255)","targetColor":"rgb(149,220,255)"},"color":"rgb(149,220,255)","size":21.0},{"source":"EPC","target":"CLX","id":"44138","attributes":{"sourceColor":"rgb(149,220,255)","targetColor":"rgb(149,220,255)"},"color":"rgb(149,220,255)","size":16.0},{"source":"PG","target":"CL","id":"44119","attributes":{"sourceColor":"rgb(149,220,255)","targetColor":"rgb(149,220,255)"},"color":"rgb(149,220,255)","size":865.0},{"source":"CTHR","target":"CLX","id":"44144","attributes":{"sourceColor":"rgb(149,220,255)","targetColor":"rgb(149,220,255)"},"color":"rgb(149,220,255)","size":10.0},{"source":"WULF","target":"KODK","id":"44285","attributes":{"sourceColor":"rgb(149,220,255)","targetColor":"rgb(149,220,255)"},"color":"rgb(149,220,255)","size":1083.0},{"source":"GLW","target":"AOS","id":"44057","attributes":{"sourceColor":"rgb(149,220,255)","targetColor":"rgb(149,220,255)"},"color":"rgb(149,220,255)","size":82.0},{"source":"LEG","target":"CL","id":"44123","attributes":{"sourceColor":"rgb(149,220,255)","targetColor":"rgb(149,220,255)"},"color":"rgb(149,220,255)","size":45.0},{"source":"SNBR","target":"NUS","id":"44319","attributes":{"sourceColor":"rgb(149,220,255)","targetColor":"rgb(149,220,255)"},"color":"rgb(149,220,255)","size":4.0},{"source":"GLW","target":"EL","id":"44198","attributes":{"sourceColor":"rgb(149,220,255)","targetColor":"rgb(149,220,255)"},"color":"rgb(149,220,255)","size":5.0},{"source":"SPB","target":"MOV","id":"44312","attributes":{"sourceColor":"rgb(149,220,255)","targetColor":"rgb(149,220,255)"},"color":"rgb(149,220,255)","size":2.0},{"source":"TPX","target":"HOG","id":"44268","attributes":{"sourceColor":"rgb(149,220,255)","targetColor":"rgb(149,220,255)"},"color":"rgb(149,220,255)","size":2.0},{"source":"ECL","target":"BRDS","id":"44095","attributes":{"sourceColor":"rgb(149,220,255)","targetColor":"rgb(149,220,255)"},"color":"rgb(149,220,255)","size":2.0},{"source":"PG","target":"HOFT","id":"44258","attributes":{"sourceColor":"rgb(149,220,255)","targetColor":"rgb(149,220,255)"},"color":"rgb(149,220,255)","size":2.0},{"source":"WHR","target":"MOV","id":"44308","attributes":{"sourceColor":"rgb(149,220,255)","targetColor":"rgb(149,220,255)"},"color":"rgb(149,220,255)","size":2.0},{"source":"MOV","target":"FOSL","id":"44234","attributes":{"sourceColor":"rgb(149,220,255)","targetColor":"rgb(149,220,255)"},"color":"rgb(149,220,255)","size":10.0},{"source":"NC","target":"KODK","id":"44280","attributes":{"sourceColor":"rgb(149,220,255)","targetColor":"rgb(149,220,255)"},"color":"rgb(149,220,255)","size":1.0},{"source":"KODK","target":"FORD","id":"44233","attributes":{"sourceColor":"rgb(149,220,255)","targetColor":"rgb(149,220,255)"},"color":"rgb(149,220,255)","size":2.0},{"source":"WHR","target":"TPR","id":"44387","attributes":{"sourceColor":"rgb(149,220,255)","targetColor":"rgb(149,220,255)"},"color":"rgb(149,220,255)","size":4.0},{"source":"WULF","target":"MITQ","id":"44306","attributes":{"sourceColor":"rgb(149,220,255)","targetColor":"rgb(149,220,255)"},"color":"rgb(149,220,255)","size":8.0},{"source":"SPB","target":"EL","id":"44202","attributes":{"sourceColor":"rgb(149,220,255)","targetColor":"rgb(149,220,255)"},"color":"rgb(149,220,255)","size":14.0},{"source":"PG","target":"DFFN","id":"44180","attributes":{"sourceColor":"rgb(149,220,255)","targetColor":"rgb(149,220,255)"},"color":"rgb(149,220,255)","size":2.0},{"source":"ECL","target":"CHD","id":"44107","attributes":{"sourceColor":"rgb(149,220,255)","targetColor":"rgb(149,220,255)"},"color":"rgb(149,220,255)","size":161.0},{"source":"CL","target":"APOG","id":"44088","attributes":{"sourceColor":"rgb(149,220,255)","targetColor":"rgb(149,220,255)"},"color":"rgb(149,220,255)","size":18.0},{"source":"CHD","target":"APOG","id":"44084","attributes":{"sourceColor":"rgb(149,220,255)","targetColor":"rgb(149,220,255)"},"color":"rgb(149,220,255)","size":102.0},{"source":"TPX","target":"TPR","id":"44377","attributes":{"sourceColor":"rgb(149,220,255)","targetColor":"rgb(149,220,255)"},"color":"rgb(149,220,255)","size":28.0},{"source":"COTY","target":"BRDS","id":"44096","attributes":{"sourceColor":"rgb(149,220,255)","targetColor":"rgb(149,220,255)"},"color":"rgb(149,220,255)","size":2.0},{"source":"PG","target":"LEG","id":"44297","attributes":{"sourceColor":"rgb(149,220,255)","targetColor":"rgb(149,220,255)"},"color":"rgb(149,220,255)","size":56.0},{"source":"FORD","target":"FLXS","id":"44226","attributes":{"sourceColor":"rgb(149,220,255)","targetColor":"rgb(149,220,255)"},"color":"rgb(149,220,255)","size":2.0},{"source":"TPX","target":"HOFT","id":"44259","attributes":{"sourceColor":"rgb(149,220,255)","targetColor":"rgb(149,220,255)"},"color":"rgb(149,220,255)","size":2.0},{"source":"HOG","target":"BRDS","id":"44097","attributes":{"sourceColor":"rgb(149,220,255)","targetColor":"rgb(149,220,255)"},"color":"rgb(149,220,255)","size":3.0},{"source":"CLX","target":"APD","id":"44079","attributes":{"sourceColor":"rgb(149,220,255)","targetColor":"rgb(149,220,255)"},"color":"rgb(149,220,255)","size":120.0},{"source":"SPB","target":"EPC","id":"44215","attributes":{"sourceColor":"rgb(149,220,255)","targetColor":"rgb(149,220,255)"},"color":"rgb(149,220,255)","size":4.0},{"source":"PG","target":"APOG","id":"44091","attributes":{"sourceColor":"rgb(149,220,255)","targetColor":"rgb(149,220,255)"},"color":"rgb(149,220,255)","size":18.0},{"source":"CL","target":"WULF","id":"44438","attributes":{"sourceColor":"rgb(149,220,255)","targetColor":"rgb(149,220,255)"},"color":"rgb(149,220,255)","size":1.0},{"source":"HOG","target":"AOS","id":"44058","attributes":{"sourceColor":"rgb(149,220,255)","targetColor":"rgb(149,220,255)"},"color":"rgb(149,220,255)","size":4.0},{"source":"HOG","target":"CTHR","id":"44177","attributes":{"sourceColor":"rgb(149,220,255)","targetColor":"rgb(149,220,255)"},"color":"rgb(149,220,255)","size":19.0},{"source":"PG","target":"GLW","id":"44244","attributes":{"sourceColor":"rgb(149,220,255)","targetColor":"rgb(149,220,255)"},"color":"rgb(149,220,255)","size":6.0},{"source":"APD","target":"AOS","id":"44056","attributes":{"sourceColor":"rgb(149,220,255)","targetColor":"rgb(149,220,255)"},"color":"rgb(149,220,255)","size":246.0},{"source":"WEBR","target":"COOK","id":"44159","attributes":{"sourceColor":"rgb(149,220,255)","targetColor":"rgb(149,220,255)"},"color":"rgb(149,220,255)","size":18.0},{"source":"TPR","target":"COTY","id":"44172","attributes":{"sourceColor":"rgb(149,220,255)","targetColor":"rgb(149,220,255)"},"color":"rgb(149,220,255)","size":4.0},{"source":"ECL","target":"APOG","id":"44087","attributes":{"sourceColor":"rgb(149,220,255)","targetColor":"rgb(149,220,255)"},"color":"rgb(149,220,255)","size":62.0},{"source":"APOG","target":"APD","id":"44076","attributes":{"sourceColor":"rgb(149,220,255)","targetColor":"rgb(149,220,255)"},"color":"rgb(149,220,255)","size":102.0},{"source":"NC","target":"HOG","id":"44272","attributes":{"sourceColor":"rgb(149,220,255)","targetColor":"rgb(149,220,255)"},"color":"rgb(149,220,255)","size":1.0},{"source":"MOV","target":"ECL","id":"44192","attributes":{"sourceColor":"rgb(149,220,255)","targetColor":"rgb(149,220,255)"},"color":"rgb(149,220,255)","size":2.0},{"source":"TPR","target":"APOG","id":"44089","attributes":{"sourceColor":"rgb(149,220,255)","targetColor":"rgb(149,220,255)"},"color":"rgb(149,220,255)","size":6.0},{"source":"EL","target":"CLX","id":"44141","attributes":{"sourceColor":"rgb(149,220,255)","targetColor":"rgb(149,220,255)"},"color":"rgb(149,220,255)","size":365.0},{"source":"COTY","target":"CL","id":"44122","attributes":{"sourceColor":"rgb(149,220,255)","targetColor":"rgb(149,220,255)"},"color":"rgb(149,220,255)","size":18.0},{"source":"GLW","target":"APOG","id":"44083","attributes":{"sourceColor":"rgb(149,220,255)","targetColor":"rgb(149,220,255)"},"color":"rgb(149,220,255)","size":42.0},{"source":"TPR","target":"FOSL","id":"44236","attributes":{"sourceColor":"rgb(149,220,255)","targetColor":"rgb(149,220,255)"},"color":"rgb(149,220,255)","size":31.0},{"source":"HOFT","target":"COTY","id":"44162","attributes":{"sourceColor":"rgb(149,220,255)","targetColor":"rgb(149,220,255)"},"color":"rgb(149,220,255)","size":2.0},{"source":"KODK","target":"COOK","id":"44152","attributes":{"sourceColor":"rgb(149,220,255)","targetColor":"rgb(149,220,255)"},"color":"rgb(149,220,255)","size":15.0},{"source":"LEG","target":"CHD","id":"44113","attributes":{"sourceColor":"rgb(149,220,255)","targetColor":"rgb(149,220,255)"},"color":"rgb(149,220,255)","size":56.0},{"source":"PG","target":"CLX","id":"44137","attributes":{"sourceColor":"rgb(149,220,255)","targetColor":"rgb(149,220,255)"},"color":"rgb(149,220,255)","size":438.0},{"source":"WHR","target":"ECL","id":"44196","attributes":{"sourceColor":"rgb(149,220,255)","targetColor":"rgb(149,220,255)"},"color":"rgb(149,220,255)","size":6.0},{"source":"LEG","target":"AOS","id":"44061","attributes":{"sourceColor":"rgb(149,220,255)","targetColor":"rgb(149,220,255)"},"color":"rgb(149,220,255)","size":12.0},{"source":"WHR","target":"TPX","id":"44399","attributes":{"sourceColor":"rgb(149,220,255)","targetColor":"rgb(149,220,255)"},"color":"rgb(149,220,255)","size":2.0},{"source":"NUS","target":"CLX","id":"44148","attributes":{"sourceColor":"rgb(149,220,255)","targetColor":"rgb(149,220,255)"},"color":"rgb(149,220,255)","size":2.0},{"source":"NUS","target":"EL","id":"44204","attributes":{"sourceColor":"rgb(149,220,255)","targetColor":"rgb(149,220,255)"},"color":"rgb(149,220,255)","size":16.0},{"source":"WHR","target":"NC","id":"44316","attributes":{"sourceColor":"rgb(149,220,255)","targetColor":"rgb(149,220,255)"},"color":"rgb(149,220,255)","size":4.0},{"source":"TPR","target":"CL","id":"44133","attributes":{"sourceColor":"rgb(149,220,255)","targetColor":"rgb(149,220,255)"},"color":"rgb(149,220,255)","size":8.0},{"source":"PG","target":"AOS","id":"44062","attributes":{"sourceColor":"rgb(149,220,255)","targetColor":"rgb(149,220,255)"},"color":"rgb(149,220,255)","size":35.0},{"source":"HOG","target":"APD","id":"44067","attributes":{"sourceColor":"rgb(149,220,255)","targetColor":"rgb(149,220,255)"},"color":"rgb(149,220,255)","size":42.0},{"source":"MITQ","target":"COOK","id":"44153","attributes":{"sourceColor":"rgb(149,220,255)","targetColor":"rgb(149,220,255)"},"color":"rgb(149,220,255)","size":2.0},{"source":"CLX","target":"CHD","id":"44109","attributes":{"sourceColor":"rgb(149,220,255)","targetColor":"rgb(149,220,255)"},"color":"rgb(149,220,255)","size":213.0},{"source":"HOG","target":"CLX","id":"44150","attributes":{"sourceColor":"rgb(149,220,255)","targetColor":"rgb(149,220,255)"},"color":"rgb(149,220,255)","size":2.0},{"source":"TPR","target":"HOG","id":"44261","attributes":{"sourceColor":"rgb(149,220,255)","targetColor":"rgb(149,220,255)"},"color":"rgb(149,220,255)","size":2.0},{"source":"KVUE","target":"PG","id":"44348","attributes":{"sourceColor":"rgb(149,220,255)","targetColor":"rgb(149,220,255)"},"color":"rgb(149,220,255)","size":1.0},{"source":"ECL","target":"COTY","id":"44167","attributes":{"sourceColor":"rgb(149,220,255)","targetColor":"rgb(149,220,255)"},"color":"rgb(149,220,255)","size":2.0},{"source":"WEBR","target":"SNBR","id":"44357","attributes":{"sourceColor":"rgb(149,220,255)","targetColor":"rgb(149,220,255)"},"color":"rgb(149,220,255)","size":4.0},{"source":"WULF","target":"WEBR","id":"44400","attributes":{"sourceColor":"rgb(149,220,255)","targetColor":"rgb(149,220,255)"},"color":"rgb(149,220,255)","size":4.0},{"source":"WHR","target":"HOG","id":"44265","attributes":{"sourceColor":"rgb(149,220,255)","targetColor":"rgb(149,220,255)"},"color":"rgb(149,220,255)","size":10.0},{"source":"WULF","target":"TPX","id":"44391","attributes":{"sourceColor":"rgb(149,220,255)","targetColor":"rgb(149,220,255)"},"color":"rgb(149,220,255)","size":2.0},{"source":"PG","target":"APD","id":"44078","attributes":{"sourceColor":"rgb(149,220,255)","targetColor":"rgb(149,220,255)"},"color":"rgb(149,220,255)","size":137.0},{"source":"GLW","target":"CHD","id":"44112","attributes":{"sourceColor":"rgb(149,220,255)","targetColor":"rgb(149,220,255)"},"color":"rgb(149,220,255)","size":67.0},{"source":"WHR","target":"EL","id":"44214","attributes":{"sourceColor":"rgb(149,220,255)","targetColor":"rgb(149,220,255)"},"color":"rgb(149,220,255)","size":8.0},{"source":"LEG","target":"HOFT","id":"44253","attributes":{"sourceColor":"rgb(149,220,255)","targetColor":"rgb(149,220,255)"},"color":"rgb(149,220,255)","size":19.0},{"source":"CL","target":"AOS","id":"44054","attributes":{"sourceColor":"rgb(149,220,255)","targetColor":"rgb(149,220,255)"},"color":"rgb(149,220,255)","size":95.0},{"source":"EL","target":"CHD","id":"44105","attributes":{"sourceColor":"rgb(149,220,255)","targetColor":"rgb(149,220,255)"},"color":"rgb(149,220,255)","size":36.0},{"source":"WULF","target":"HOG","id":"44263","attributes":{"sourceColor":"rgb(149,220,255)","targetColor":"rgb(149,220,255)"},"color":"rgb(149,220,255)","size":7.0},{"source":"CL","target":"BRDS","id":"44092","attributes":{"sourceColor":"rgb(149,220,255)","targetColor":"rgb(149,220,255)"},"color":"rgb(149,220,255)","size":2.0},{"source":"WHR","target":"AOS","id":"44053","attributes":{"sourceColor":"rgb(149,220,255)","targetColor":"rgb(149,220,255)"},"color":"rgb(149,220,255)","size":20.0},{"source":"WHR","target":"COTY","id":"44166","attributes":{"sourceColor":"rgb(149,220,255)","targetColor":"rgb(149,220,255)"},"color":"rgb(149,220,255)","size":4.0},{"source":"MITQ","target":"ECL","id":"44185","attributes":{"sourceColor":"rgb(149,220,255)","targetColor":"rgb(149,220,255)"},"color":"rgb(149,220,255)","size":2.0},{"source":"FLXS","target":"DFFN","id":"44182","attributes":{"sourceColor":"rgb(149,220,255)","targetColor":"rgb(149,220,255)"},"color":"rgb(149,220,255)","size":4.0},{"source":"TPR","target":"MOV","id":"44310","attributes":{"sourceColor":"rgb(149,220,255)","targetColor":"rgb(149,220,255)"},"color":"rgb(149,220,255)","size":6.0},{"source":"WEBR","target":"TPX","id":"44389","attributes":{"sourceColor":"rgb(149,220,255)","targetColor":"rgb(149,220,255)"},"color":"rgb(149,220,255)","size":2.0},{"source":"FOSL","target":"FORD","id":"44231","attributes":{"sourceColor":"rgb(149,220,255)","targetColor":"rgb(149,220,255)"},"color":"rgb(149,220,255)","size":2.0},{"source":"TPX","target":"COOK","id":"44154","attributes":{"sourceColor":"rgb(149,220,255)","targetColor":"rgb(149,220,255)"},"color":"rgb(149,220,255)","size":2.0},{"source":"NUS","target":"NC","id":"44318","attributes":{"sourceColor":"rgb(149,220,255)","targetColor":"rgb(149,220,255)"},"color":"rgb(149,220,255)","size":8.0},{"source":"HOG","target":"COTY","id":"44164","attributes":{"sourceColor":"rgb(149,220,255)","targetColor":"rgb(149,220,255)"},"color":"rgb(149,220,255)","size":8.0},{"source":"HOFT","target":"APOG","id":"44082","attributes":{"sourceColor":"rgb(149,220,255)","targetColor":"rgb(149,220,255)"},"color":"rgb(149,220,255)","size":6.0},{"source":"TPX","target":"COTY","id":"44176","attributes":{"sourceColor":"rgb(149,220,255)","targetColor":"rgb(149,220,255)"},"color":"rgb(149,220,255)","size":5.0},{"source":"CLX","target":"AOS","id":"44060","attributes":{"sourceColor":"rgb(149,220,255)","targetColor":"rgb(149,220,255)"},"color":"rgb(149,220,255)","size":104.0},{"source":"ODC","target":"NC","id":"44314","attributes":{"sourceColor":"rgb(149,220,255)","targetColor":"rgb(149,220,255)"},"color":"rgb(149,220,255)","size":2.0},{"source":"FORD","target":"COTY","id":"44165","attributes":{"sourceColor":"rgb(149,220,255)","targetColor":"rgb(149,220,255)"},"color":"rgb(149,220,255)","size":2.0},{"source":"HOG","target":"HBB","id":"44251","attributes":{"sourceColor":"rgb(149,220,255)","targetColor":"rgb(149,220,255)"},"color":"rgb(149,220,255)","size":2.0}]}